<?xml version="1.0" encoding="UTF-8" standalone="yes"?>
<Wordlist>
    <Paradigm pdgId="0" Lemma="але´ньчык" Tag="NCAINM1">
        <Form Tag="NS">але´ньчык</Form>
        <Form Tag="GS">але´ньчыка</Form>
        <Form Tag="DS">але´ньчыку</Form>
        <Form Tag="AS">але´ньчыка</Form>
        <Form Tag="IS">але´ньчыкам</Form>
        <Form Tag="LS">але´ньчыку</Form>
        <Form Tag="NP">але´ньчыкі</Form>
        <Form Tag="GP">але´ньчыкаў</Form>
        <Form Tag="DP">але´ньчыкам</Form>
        <Form Tag="AP">але´ньчыкаў</Form>
        <Form Tag="IP">але´ньчыкамі</Form>
        <Form Tag="LP">але´ньчыках</Form>
    </Paradigm>
    <Paradigm pdgId="0" Lemma="алеепадо´бны" Tag="ARP">
        <Form Tag="MNS">алеепадо´бны</Form>
        <Form Tag="MGS">алеепадо´бнага</Form>
        <Form Tag="MDS">алеепадо´бнаму</Form>
        <Form Tag="MAS">алеепадо´бны</Form>
        <Form Tag="MAS">алеепадо´бнага</Form>
        <Form Tag="MIS">алеепадо´бным</Form>
        <Form Tag="MLS">алеепадо´бным</Form>
        <Form Tag="NNS">алеепадо´бнае</Form>
        <Form Tag="NGS">алеепадо´бнага</Form>
        <Form Tag="NDS">алеепадо´бнаму</Form>
        <Form Tag="NAS">алеепадо´бнае</Form>
        <Form Tag="NIS">алеепадо´бным</Form>
        <Form Tag="NLS">алеепадо´бным</Form>
        <Form Tag="FNS">алеепадо´бная</Form>
        <Form Tag="FGS">алеепадо´бнай</Form>
        <Form Tag="FGS">алеепадо´бнае</Form>
        <Form Tag="FDS">алеепадо´бнай</Form>
        <Form Tag="FAS">алеепадо´бную</Form>
        <Form Tag="FIS">алеепадо´бнай</Form>
        <Form Tag="FIS">алеепадо´бнаю</Form>
        <Form Tag="FLS">алеепадо´бнай</Form>
        <Form Tag="PNP">алеепадо´бныя</Form>
        <Form Tag="PGP">алеепадо´бных</Form>
        <Form Tag="PDP">алеепадо´бным</Form>
        <Form Tag="PAP">алеепадо´бныя</Form>
        <Form Tag="PIP">алеепадо´бнымі</Form>
        <Form Tag="PLP">алеепадо´бных</Form>
    </Paradigm>
    <Paradigm pdgId="0" Lemma="алейкемі´чны" Tag="ARP">
        <Form Tag="MNS">алейкемі´чны</Form>
        <Form Tag="MGS">алейкемі´чнага</Form>
        <Form Tag="MDS">алейкемі´чнаму</Form>
        <Form Tag="MAS">алейкемі´чны</Form>
        <Form Tag="MAS">алейкемі´чнага</Form>
        <Form Tag="MIS">алейкемі´чным</Form>
        <Form Tag="MLS">алейкемі´чным</Form>
        <Form Tag="NNS">алейкемі´чнае</Form>
        <Form Tag="NGS">алейкемі´чнага</Form>
        <Form Tag="NDS">алейкемі´чнаму</Form>
        <Form Tag="NAS">алейкемі´чнае</Form>
        <Form Tag="NIS">алейкемі´чным</Form>
        <Form Tag="NLS">алейкемі´чным</Form>
        <Form Tag="FNS">алейкемі´чная</Form>
        <Form Tag="FGS">алейкемі´чнай</Form>
        <Form Tag="FGS">алейкемі´чнае</Form>
        <Form Tag="FDS">алейкемі´чнай</Form>
        <Form Tag="FAS">алейкемі´чную</Form>
        <Form Tag="FIS">алейкемі´чнай</Form>
        <Form Tag="FIS">алейкемі´чнаю</Form>
        <Form Tag="FLS">алейкемі´чнай</Form>
        <Form Tag="PNP">алейкемі´чныя</Form>
        <Form Tag="PGP">алейкемі´чных</Form>
        <Form Tag="PDP">алейкемі´чным</Form>
        <Form Tag="PAP">алейкемі´чныя</Form>
        <Form Tag="PIP">алейкемі´чнымі</Form>
        <Form Tag="PLP">алейкемі´чных</Form>
    </Paradigm>
    <Paradigm pdgId="0" Lemma="алейкемі´я" Tag="NCIINF2">
        <Form Tag="NS">алейкемі´я</Form>
        <Form Tag="GS">алейкемі´і</Form>
        <Form Tag="DS">алейкемі´і</Form>
        <Form Tag="AS">алейкемі´ю</Form>
        <Form Tag="IS">алейкемі´яй</Form>
        <Form Tag="IS">алейкемі´яю</Form>
        <Form Tag="LS">алейкемі´і</Form>
    </Paradigm>
    <Paradigm pdgId="0" Lemma="александры´йка" Tag="NCIINF2">
        <Form Tag="NS">александры´йка</Form>
        <Form Tag="GS">александры´йкі</Form>
        <Form Tag="DS">александры´йцы</Form>
        <Form Tag="AS">александры´йку</Form>
        <Form Tag="IS">александры´йкай</Form>
        <Form Tag="IS">александры´йкаю</Form>
        <Form Tag="LS">александры´йцы</Form>
    </Paradigm>
    <Paradigm pdgId="0" Lemma="алеяно´сны" Tag="ARP">
        <Form Tag="MNS">алеяно´сны</Form>
        <Form Tag="MGS">алеяно´снага</Form>
        <Form Tag="MDS">алеяно´снаму</Form>
        <Form Tag="MAS">алеяно´сны</Form>
        <Form Tag="MAS">алеяно´снага</Form>
        <Form Tag="MIS">алеяно´сным</Form>
        <Form Tag="MLS">алеяно´сным</Form>
        <Form Tag="NNS">алеяно´снае</Form>
        <Form Tag="NGS">алеяно´снага</Form>
        <Form Tag="NDS">алеяно´снаму</Form>
        <Form Tag="NAS">алеяно´снае</Form>
        <Form Tag="NIS">алеяно´сным</Form>
        <Form Tag="NLS">алеяно´сным</Form>
        <Form Tag="FNS">алеяно´сная</Form>
        <Form Tag="FGS">алеяно´снай</Form>
        <Form Tag="FGS">алеяно´снае</Form>
        <Form Tag="FDS">алеяно´снай</Form>
        <Form Tag="FAS">алеяно´сную</Form>
        <Form Tag="FIS">алеяно´снай</Form>
        <Form Tag="FIS">алеяно´снаю</Form>
        <Form Tag="FLS">алеяно´снай</Form>
        <Form Tag="PNP">алеяно´сныя</Form>
        <Form Tag="PGP">алеяно´сных</Form>
        <Form Tag="PDP">алеяно´сным</Form>
        <Form Tag="PAP">алеяно´сныя</Form>
        <Form Tag="PIP">алеяно´снымі</Form>
        <Form Tag="PLP">алеяно´сных</Form>
    </Paradigm>
    <Paradigm pdgId="0" Lemma="алкагалізава´ць" Tag="VTMN1">
        <Form Tag="0">алкагалізава´ць</Form>
        <Form Tag="R1S">алкагалізу´ю</Form>
        <Form Tag="R2S">алкагалізу´еш</Form>
        <Form Tag="R3S">алкагалізу´е</Form>
        <Form Tag="R1P">алкагалізу´ем</Form>
        <Form Tag="R2P">алкагалізу´еце</Form>
        <Form Tag="R3P">алкагалізу´юць</Form>
        <Form Tag="PXSM">алкагалізава´ў</Form>
        <Form Tag="PXSF">алкагалізава´ла</Form>
        <Form Tag="PXSN">алкагалізава´ла</Form>
        <Form Tag="PXPX">алкагалізава´лі</Form>
        <Form Tag="I2S">алкагалізу´й</Form>
        <Form Tag="I2P">алкагалізу´йце</Form>
        <Form Tag="RG">алкагалізу´ючы</Form>
    </Paradigm>
    <Paradigm pdgId="0" Lemma="алкагалізава´ць" Tag="VTPN1">
        <Form Tag="0">алкагалізава´ць</Form>
        <Form Tag="F1S">алкагалізу´ю</Form>
        <Form Tag="F2S">алкагалізу´еш</Form>
        <Form Tag="F3S">алкагалізу´е</Form>
        <Form Tag="F1P">алкагалізу´ем</Form>
        <Form Tag="F2P">алкагалізу´еце</Form>
        <Form Tag="F3P">алкагалізу´юць</Form>
        <Form Tag="PXSM">алкагалізава´ў</Form>
        <Form Tag="PXSF">алкагалізава´ла</Form>
        <Form Tag="PXSN">алкагалізава´ла</Form>
        <Form Tag="PXPX">алкагалізава´лі</Form>
        <Form Tag="I2S">алкагалізу´й</Form>
        <Form Tag="I2P">алкагалізу´йце</Form>
        <Form Tag="PG">алкагалізава´ўшы</Form>
    </Paradigm>
    <Paradigm pdgId="0" Lemma="алкара´н" Tag="NPIINM1">
        <Form Tag="NS">алкара´н</Form>
        <Form Tag="GS">алкара´на</Form>
        <Form Tag="DS">алкара´ну</Form>
        <Form Tag="AS">алкара´н</Form>
        <Form Tag="IS">алкара´нам</Form>
        <Form Tag="LS">алкара´не</Form>
    </Paradigm>
    <Paradigm pdgId="0" Lemma="ало´д" Tag="NCIINM1">
        <Form Tag="NS">ало´д</Form>
        <Form Tag="GS">ало´да</Form>
        <Form Tag="DS">ало´ду</Form>
        <Form Tag="AS">ало´д</Form>
        <Form Tag="IS">ало´дам</Form>
        <Form Tag="LS">ало´дзе</Form>
    </Paradigm>
    <Paradigm pdgId="0" Lemma="альмаві´ва" Tag="NCIINF2">
        <Form Tag="NS">альмаві´ва</Form>
        <Form Tag="GS">альмаві´вы</Form>
        <Form Tag="DS">альмаві´ве</Form>
        <Form Tag="AS">альмаві´ву</Form>
        <Form Tag="IS">альмаві´вай</Form>
        <Form Tag="IS">альмаві´ваю</Form>
        <Form Tag="LS">альмаві´ве</Form>
        <Form Tag="NP">альмаві´вы</Form>
        <Form Tag="GP">альмаві´ў</Form>
        <Form Tag="DP">альмаві´вам</Form>
        <Form Tag="AP">альмаві´вы</Form>
        <Form Tag="IP">альмаві´вамі</Form>
        <Form Tag="LP">альмаві´вах</Form>
    </Paradigm>
    <Paradigm pdgId="0" Lemma="альты´стыка" Tag="NCIINF2">
        <Form Tag="NS">альты´стыка</Form>
        <Form Tag="GS">альты´стыкі</Form>
        <Form Tag="DS">альты´стыцы</Form>
        <Form Tag="AS">альты´стыку</Form>
        <Form Tag="IS">альты´стыкай</Form>
        <Form Tag="IS">альты´стыкаю</Form>
        <Form Tag="LS">альты´стыцы</Form>
    </Paradigm>
    <Paradigm pdgId="0" Lemma="альфаме´тр" Tag="NCIINM1">
        <Form Tag="NS">альфаме´тр</Form>
        <Form Tag="GS">альфаме´тра</Form>
        <Form Tag="DS">альфаме´тру</Form>
        <Form Tag="AS">альфаме´тр</Form>
        <Form Tag="IS">альфаме´трам</Form>
        <Form Tag="LS">альфаме´тры</Form>
        <Form Tag="NP">альфаме´тры</Form>
        <Form Tag="GP">альфаме´траў</Form>
        <Form Tag="DP">альфаме´трам</Form>
        <Form Tag="AP">альфаме´тры</Form>
        <Form Tag="IP">альфаме´трамі</Form>
        <Form Tag="LP">альфаме´трах</Form>
    </Paradigm>
    <Paradigm pdgId="0" Lemma="альфо´ль" Tag="NCIIBF3">
        <Form Tag="NS">альфо´ль</Form>
        <Form Tag="GS">альфо´лі</Form>
        <Form Tag="DS">альфо´лі</Form>
        <Form Tag="AS">альфо´ль</Form>
        <Form Tag="IS">альфо´ллю</Form>
        <Form Tag="LS">альфо´лі</Form>
    </Paradigm>
    <Paradigm pdgId="0" Lemma="алё´нка" Tag="NCAINF2">
        <Form Tag="NS">алё´нка</Form>
        <Form Tag="GS">алё´нкі</Form>
        <Form Tag="DS">алё´нцы</Form>
        <Form Tag="AS">алё´нку</Form>
        <Form Tag="IS">алё´нкай</Form>
        <Form Tag="IS">алё´нкаю</Form>
        <Form Tag="LS">алё´нцы</Form>
        <Form Tag="NP">алё´нкі</Form>
        <Form Tag="GP">алё´нак</Form>
        <Form Tag="DP">алё´нкам</Form>
        <Form Tag="AP">алё´нак</Form>
        <Form Tag="IP">алё´нкамі</Form>
        <Form Tag="LP">алё´нках</Form>
    </Paradigm>
    <Paradigm pdgId="0" Lemma="аліме´нтавы" Tag="ARP">
        <Form Tag="MNS">аліме´нтавы</Form>
        <Form Tag="MGS">аліме´нтавага</Form>
        <Form Tag="MDS">аліме´нтаваму</Form>
        <Form Tag="MAS">аліме´нтавы</Form>
        <Form Tag="MIS">аліме´нтавым</Form>
        <Form Tag="MLS">аліме´нтавым</Form>
        <Form Tag="NNS">аліме´нтавае</Form>
        <Form Tag="NGS">аліме´нтавага</Form>
        <Form Tag="NDS">аліме´нтаваму</Form>
        <Form Tag="NAS">аліме´нтавае</Form>
        <Form Tag="NIS">аліме´нтавым</Form>
        <Form Tag="NLS">аліме´нтавым</Form>
        <Form Tag="FNS">аліме´нтавая</Form>
        <Form Tag="FGS">аліме´нтавай</Form>
        <Form Tag="FGS">аліме´нтавае</Form>
        <Form Tag="FDS">аліме´нтавай</Form>
        <Form Tag="FAS">аліме´нтавую</Form>
        <Form Tag="FIS">аліме´нтавай</Form>
        <Form Tag="FIS">аліме´нтаваю</Form>
        <Form Tag="FLS">аліме´нтавай</Form>
        <Form Tag="PNP">аліме´нтавыя</Form>
        <Form Tag="PGP">аліме´нтавых</Form>
        <Form Tag="PDP">аліме´нтавым</Form>
        <Form Tag="PAP">аліме´нтавыя</Form>
        <Form Tag="PIP">аліме´нтавымі</Form>
        <Form Tag="PLP">аліме´нтавых</Form>
    </Paradigm>
    <Paradigm pdgId="0" Lemma="ама´таршчына" Tag="NCIINF2">
        <Form Tag="NS">ама´таршчына</Form>
        <Form Tag="GS">ама´таршчыны</Form>
        <Form Tag="DS">ама´таршчыне</Form>
        <Form Tag="AS">ама´таршчыну</Form>
        <Form Tag="IS">ама´таршчынай</Form>
        <Form Tag="IS">ама´таршчынаю</Form>
        <Form Tag="LS">ама´таршчыне</Form>
    </Paradigm>
    <Paradigm pdgId="0" Lemma="амальга´мвальны" Tag="ARP">
        <Form Tag="MNS">амальга´мвальны</Form>
        <Form Tag="MGS">амальга´мвальнага</Form>
        <Form Tag="MDS">амальга´мвальнаму</Form>
        <Form Tag="MAS">амальга´мвальны</Form>
        <Form Tag="MAS">амальга´мвальнага</Form>
        <Form Tag="MIS">амальга´мвальным</Form>
        <Form Tag="MLS">амальга´мвальным</Form>
        <Form Tag="NNS">амальга´мвальнае</Form>
        <Form Tag="NGS">амальга´мвальнага</Form>
        <Form Tag="NDS">амальга´мвальнаму</Form>
        <Form Tag="NAS">амальга´мвальнае</Form>
        <Form Tag="NIS">амальга´мвальным</Form>
        <Form Tag="NLS">амальга´мвальным</Form>
        <Form Tag="FNS">амальга´мвальная</Form>
        <Form Tag="FGS">амальга´мвальнай</Form>
        <Form Tag="FGS">амальга´мвальнае</Form>
        <Form Tag="FDS">амальга´мвальнай</Form>
        <Form Tag="FAS">амальга´мвальную</Form>
        <Form Tag="FIS">амальга´мвальнай</Form>
        <Form Tag="FIS">амальга´мвальнаю</Form>
        <Form Tag="FLS">амальга´мвальнай</Form>
        <Form Tag="PNP">амальга´мвальныя</Form>
        <Form Tag="PGP">амальга´мвальных</Form>
        <Form Tag="PDP">амальга´мвальным</Form>
        <Form Tag="PAP">амальга´мвальныя</Form>
        <Form Tag="PIP">амальга´мвальнымі</Form>
        <Form Tag="PLP">амальга´мвальных</Form>
    </Paradigm>
    <Paradigm pdgId="0" Lemma="амана´т" Tag="NCAPNM1">
        <Form Tag="NS">амана´т</Form>
        <Form Tag="GS">амана´та</Form>
        <Form Tag="DS">амана´ту</Form>
        <Form Tag="AS">амана´та</Form>
        <Form Tag="IS">амана´там</Form>
        <Form Tag="LS">амана´ту</Form>
        <Form Tag="LS">амана´це</Form>
        <Form Tag="NP">амана´ты</Form>
        <Form Tag="GP">амана´таў</Form>
        <Form Tag="DP">амана´там</Form>
        <Form Tag="AP">амана´таў</Form>
        <Form Tag="IP">амана´тамі</Form>
        <Form Tag="LP">амана´тах</Form>
    </Paradigm>
    <Paradigm pdgId="0" Lemma="амафо´р" Tag="NCIINM1">
        <Form Tag="NS">амафо´р</Form>
        <Form Tag="GS">амафо´ра</Form>
        <Form Tag="DS">амафо´ру</Form>
        <Form Tag="AS">амафо´р</Form>
        <Form Tag="IS">амафо´рам</Form>
        <Form Tag="LS">амафо´ры</Form>
        <Form Tag="NP">амафо´ры</Form>
        <Form Tag="GP">амафо´раў</Form>
        <Form Tag="DP">амафо´рам</Form>
        <Form Tag="AP">амафо´ры</Form>
        <Form Tag="IP">амафо´рамі</Form>
        <Form Tag="LP">амафо´рах</Form>
    </Paradigm>
    <Paradigm pdgId="0" Lemma="амбрэ´" Tag="NCIINN0">
        <Form Tag="NS">амбрэ´</Form>
        <Form Tag="GS">амбрэ´</Form>
        <Form Tag="DS">амбрэ´</Form>
        <Form Tag="AS">амбрэ´</Form>
        <Form Tag="IS">амбрэ´</Form>
        <Form Tag="LS">амбрэ´</Form>
    </Paradigm>
    <Paradigm pdgId="0" Lemma="амніё´т" Tag="NCAINM1" options="usually_plurals">
        <Form Tag="NS">амніё´т</Form>
        <Form Tag="GS">амніё´та</Form>
        <Form Tag="DS">амніё´ту</Form>
        <Form Tag="AS">амніё´та</Form>
        <Form Tag="IS">амніё´там</Form>
        <Form Tag="LS">амніё´це</Form>
        <Form Tag="NP">амніё´ты</Form>
        <Form Tag="GP">амніё´таў</Form>
        <Form Tag="DP">амніё´там</Form>
        <Form Tag="AP">амніё´таў</Form>
        <Form Tag="IP">амніё´тамі</Form>
        <Form Tag="LP">амніё´тах</Form>
    </Paradigm>
    <Paradigm pdgId="0" Lemma="ампе´р-вагі" Tag="NCIINP7">
        <Form Tag="NP">ампе´р-ва´гі</Form>
        <Form Tag="GP">ампе´р-ва´гаў</Form>
        <Form Tag="DP">ампе´р-ва´гам</Form>
        <Form Tag="AP">ампе´р-ва´гі</Form>
        <Form Tag="IP">ампе´р-ва´гамі</Form>
        <Form Tag="LP">ампе´р-ва´гах</Form>
    </Paradigm>
    <Paradigm pdgId="0" Lemma="ампелало´гія" Tag="NCIINF2">
        <Form Tag="NS">ампелало´гія</Form>
        <Form Tag="GS">ампелало´гіі</Form>
        <Form Tag="DS">ампелало´гіі</Form>
        <Form Tag="AS">ампелало´гію</Form>
        <Form Tag="IS">ампелало´гіяй</Form>
        <Form Tag="IS">ампелало´гіяю</Form>
        <Form Tag="LS">ампелало´гіі</Form>
    </Paradigm>
    <Paradigm pdgId="0" Lemma="амуні´чны" Tag="ARP">
        <Form Tag="MNS">амуні´чны</Form>
        <Form Tag="MGS">амуні´чнага</Form>
        <Form Tag="MDS">амуні´чнаму</Form>
        <Form Tag="MAS">амуні´чны</Form>
        <Form Tag="MAS">амуні´чнага</Form>
        <Form Tag="MIS">амуні´чным</Form>
        <Form Tag="MLS">амуні´чным</Form>
        <Form Tag="NNS">амуні´чнае</Form>
        <Form Tag="NGS">амуні´чнага</Form>
        <Form Tag="NDS">амуні´чнаму</Form>
        <Form Tag="NAS">амуні´чнае</Form>
        <Form Tag="NIS">амуні´чным</Form>
        <Form Tag="NLS">амуні´чным</Form>
        <Form Tag="FNS">амуні´чная</Form>
        <Form Tag="FGS">амуні´чнай</Form>
        <Form Tag="FGS">амуні´чнае</Form>
        <Form Tag="FDS">амуні´чнай</Form>
        <Form Tag="FAS">амуні´чную</Form>
        <Form Tag="FIS">амуні´чнай</Form>
        <Form Tag="FIS">амуні´чнаю</Form>
        <Form Tag="FLS">амуні´чнай</Form>
        <Form Tag="PNP">амуні´чныя</Form>
        <Form Tag="PGP">амуні´чных</Form>
        <Form Tag="PDP">амуні´чным</Form>
        <Form Tag="PAP">амуні´чныя</Form>
        <Form Tag="PIP">амуні´чнымі</Form>
        <Form Tag="PLP">амуні´чных</Form>
    </Paradigm>
    <Paradigm pdgId="0" Lemma="амфітрыё´н" Tag="NCAPNM1">
        <Form Tag="NS">амфітрыё´н</Form>
        <Form Tag="GS">амфітрыё´на</Form>
        <Form Tag="DS">амфітрыё´ну</Form>
        <Form Tag="AS">амфітрыё´на</Form>
        <Form Tag="IS">амфітрыё´нам</Form>
        <Form Tag="LS">амфітрыё´не</Form>
        <Form Tag="LS">амфітрыё´ну</Form>
        <Form Tag="NP">амфітрыё´ны</Form>
        <Form Tag="GP">амфітрыё´наў</Form>
        <Form Tag="DP">амфітрыё´нам</Form>
        <Form Tag="AP">амфітрыё´наў</Form>
        <Form Tag="IP">амфітрыё´намі</Form>
        <Form Tag="LP">амфітрыё´нах</Form>
    </Paradigm>
    <Paradigm pdgId="0" Lemma="амё´бацыт" Tag="NCIINM1">
        <Form Tag="NS">амё´бацыт</Form>
        <Form Tag="GS">амё´бацыту</Form>
        <Form Tag="DS">амё´бацыту</Form>
        <Form Tag="AS">амё´бацыт</Form>
        <Form Tag="IS">амё´бацытам</Form>
        <Form Tag="LS">амё´бацыце</Form>
        <Form Tag="NP">амё´бацыты</Form>
        <Form Tag="GP">амё´бацытаў</Form>
        <Form Tag="DP">амё´бацытам</Form>
        <Form Tag="AP">амё´бацыты</Form>
        <Form Tag="IP">амё´бацытамі</Form>
        <Form Tag="LP">амё´бацытах</Form>
    </Paradigm>
    <Paradigm pdgId="0" Lemma="амі´н" Tag="E">
        <Form Tag="">амі´н</Form>
    </Paradigm>
    <Paradigm pdgId="0" Lemma="амі´н" Tag="NCIINM1" options="usually_plurals">
        <Form Tag="NS">амі´н</Form>
        <Form Tag="GS">амі´ну</Form>
        <Form Tag="DS">амі´ну</Form>
        <Form Tag="AS">амі´н</Form>
        <Form Tag="IS">амі´нам</Form>
        <Form Tag="LS">амі´не</Form>
        <Form Tag="NP">амі´ны</Form>
        <Form Tag="GP">амі´наў</Form>
        <Form Tag="DP">амі´нам</Form>
        <Form Tag="AP">амі´ны</Form>
        <Form Tag="IP">амі´намі</Form>
        <Form Tag="LP">амі´нах</Form>
    </Paradigm>
    <Paradigm pdgId="0" Lemma="аміта´л-на´трый" Tag="NCIINM1">
        <Form Tag="NS">аміта´л-на´трый</Form>
        <Form Tag="GS">аміта´л-на´трыю</Form>
        <Form Tag="DS">аміта´л-на´трыю</Form>
        <Form Tag="AS">аміта´л-на´трый</Form>
        <Form Tag="IS">аміта´л-на´трыем</Form>
        <Form Tag="LS">аміта´л-на´трыі</Form>
    </Paradigm>
    <Paradigm pdgId="0" Lemma="ана´лага-лічбавы" Tag="ARP">
        <Form Tag="MNS">ана´лага-лі´чбавы</Form>
        <Form Tag="MGS">ана´лага-лі´чбавага</Form>
        <Form Tag="MDS">ана´лага-лі´чбаваму</Form>
        <Form Tag="MAS">ана´лага-лі´чбавы</Form>
        <Form Tag="MIS">ана´лага-лі´чбавым</Form>
        <Form Tag="MLS">ана´лага-лі´чбавым</Form>
        <Form Tag="NNS">ана´лага-лі´чбавае</Form>
        <Form Tag="NGS">ана´лага-лі´чбавага</Form>
        <Form Tag="NDS">ана´лага-лі´чбаваму</Form>
        <Form Tag="NAS">ана´лага-лі´чбавае</Form>
        <Form Tag="NIS">ана´лага-лі´чбавым</Form>
        <Form Tag="NLS">ана´лага-лі´чбавым</Form>
        <Form Tag="FNS">ана´лага-лі´чбавая</Form>
        <Form Tag="FGS">ана´лага-лі´чбавай</Form>
        <Form Tag="FGS">ана´лага-лі´чбавае</Form>
        <Form Tag="FDS">ана´лага-лі´чбавай</Form>
        <Form Tag="FAS">ана´лага-лі´чбавую</Form>
        <Form Tag="FIS">ана´лага-лі´чбавай</Form>
        <Form Tag="FIS">ана´лага-лі´чбаваю</Form>
        <Form Tag="FLS">ана´лага-лі´чбавай</Form>
        <Form Tag="PNP">ана´лага-лі´чбавыя</Form>
        <Form Tag="PGP">ана´лага-лі´чбавых</Form>
        <Form Tag="PDP">ана´лага-лі´чбавым</Form>
        <Form Tag="PAP">ана´лага-лі´чбавыя</Form>
        <Form Tag="PIP">ана´лага-лі´чбавымі</Form>
        <Form Tag="PLP">ана´лага-лі´чбавых</Form>
    </Paradigm>
    <Paradigm pdgId="0" Lemma="ана´мнія" Tag="NCAINF2" options="usually_plurals">
        <Form Tag="NS">ана´мнія</Form>
        <Form Tag="GS">ана´мніі</Form>
        <Form Tag="DS">ана´мніі</Form>
        <Form Tag="AS">ана´мнію</Form>
        <Form Tag="IS">ана´мніяй</Form>
        <Form Tag="IS">ана´мніяю</Form>
        <Form Tag="LS">ана´мніі</Form>
        <Form Tag="NP">ана´мніі</Form>
        <Form Tag="GP">ана´мній</Form>
        <Form Tag="DP">ана´мніям</Form>
        <Form Tag="AP">ана´мній</Form>
        <Form Tag="IP">ана´мніямі</Form>
        <Form Tag="LP">ана´мніях</Form>
    </Paradigm>
    <Paradigm pdgId="0" Lemma="ана´рха-сіндыкалісцкі" Tag="ARP">
        <Form Tag="MNS">ана´рха-сіндыкалі´сцкі</Form>
        <Form Tag="MGS">ана´рха-сіндыкалі´сцкага</Form>
        <Form Tag="MDS">ана´рха-сіндыкалі´сцкаму</Form>
        <Form Tag="MAS">ана´рха-сіндыкалі´сцкі</Form>
        <Form Tag="MAS">ана´рха-сіндыкалі´сцкага</Form>
        <Form Tag="MIS">ана´рха-сіндыкалі´сцкім</Form>
        <Form Tag="MLS">ана´рха-сіндыкалі´сцкім</Form>
        <Form Tag="NNS">ана´рха-сіндыкалі´сцкае</Form>
        <Form Tag="NGS">ана´рха-сіндыкалі´сцкага</Form>
        <Form Tag="NDS">ана´рха-сіндыкалі´сцкаму</Form>
        <Form Tag="NAS">ана´рха-сіндыкалі´сцкае</Form>
        <Form Tag="NIS">ана´рха-сіндыкалі´сцкім</Form>
        <Form Tag="NLS">ана´рха-сіндыкалі´сцкім</Form>
        <Form Tag="FNS">ана´рха-сіндыкалі´сцкая</Form>
        <Form Tag="FGS">ана´рха-сіндыкалі´сцкай</Form>
        <Form Tag="FGS">ана´рха-сіндыкалі´сцкае</Form>
        <Form Tag="FDS">ана´рха-сіндыкалі´сцкай</Form>
        <Form Tag="FAS">ана´рха-сіндыкалі´сцкую</Form>
        <Form Tag="FIS">ана´рха-сіндыкалі´сцкай</Form>
        <Form Tag="FIS">ана´рха-сіндыкалі´сцкаю</Form>
        <Form Tag="FLS">ана´рха-сіндыкалі´сцкай</Form>
        <Form Tag="PNP">ана´рха-сіндыкалі´сцкія</Form>
        <Form Tag="PGP">ана´рха-сіндыкалі´сцкіх</Form>
        <Form Tag="PDP">ана´рха-сіндыкалі´сцкім</Form>
        <Form Tag="PAP">ана´рха-сіндыкалі´сцкія</Form>
        <Form Tag="PIP">ана´рха-сіндыкалі´сцкімі</Form>
        <Form Tag="PLP">ана´рха-сіндыкалі´сцкіх</Form>
    </Paradigm>
    <Paradigm pdgId="0" Lemma="анадзі´равацца" Tag="VIMR1">
        <Form Tag="0">анадзі´равацца</Form>
        <Form Tag="R1S" Type="potential">анадзі´руюся</Form>
        <Form Tag="R2S" Type="potential">анадзі´руешся</Form>
        <Form Tag="R3S">анадзі´руецца</Form>
        <Form Tag="R1P" Type="potential">анадзі´руемся</Form>
        <Form Tag="R2P" Type="potential">анадзі´руецеся</Form>
        <Form Tag="R3P">анадзі´руюцца</Form>
        <Form Tag="PXSM">анадзі´раваўся</Form>
        <Form Tag="PXSF">анадзі´равалася</Form>
        <Form Tag="PXSN">анадзі´равалася</Form>
        <Form Tag="PXPX">анадзі´раваліся</Form>
        <Form Tag="I2S" Type="potential">анадзі´руйся</Form>
        <Form Tag="I2P" Type="potential">анадзі´руйцеся</Form>
        <Form Tag="RG">анадзі´руючыся</Form>
    </Paradigm>
    <Paradigm pdgId="0" Lemma="аналі´ст" Tag="NCAPNM1">
        <Form Tag="NS">аналі´ст</Form>
        <Form Tag="GS">аналі´ста</Form>
        <Form Tag="DS">аналі´сту</Form>
        <Form Tag="AS">аналі´ста</Form>
        <Form Tag="IS">аналі´стам</Form>
        <Form Tag="LS">аналі´сце</Form>
        <Form Tag="NP">аналі´сты</Form>
        <Form Tag="GP">аналі´стаў</Form>
        <Form Tag="DP">аналі´стам</Form>
        <Form Tag="AP">аналі´стаў</Form>
        <Form Tag="IP">аналі´стамі</Form>
        <Form Tag="LP">аналі´стах</Form>
    </Paradigm>
    <Paradigm pdgId="0" Lemma="анані´раваць" Tag="VIMN1">
        <Form Tag="0">анані´раваць</Form>
        <Form Tag="R1S">анані´рую</Form>
        <Form Tag="R2S">анані´руеш</Form>
        <Form Tag="R3S">анані´руе</Form>
        <Form Tag="R1P">анані´руем</Form>
        <Form Tag="R2P">анані´руеце</Form>
        <Form Tag="R3P">анані´руюць</Form>
        <Form Tag="PXSM">анані´раваў</Form>
        <Form Tag="PXSF">анані´равала</Form>
        <Form Tag="PXSN">анані´равала</Form>
        <Form Tag="PXPX">анані´равалі</Form>
        <Form Tag="I2S">анані´руй</Form>
        <Form Tag="I2P">анані´руйце</Form>
        <Form Tag="RG">анані´руючы</Form>
    </Paradigm>
    <Paradigm pdgId="0" Lemma="анатамава´нне" Tag="NCIINN1">
        <Form Tag="NS">анатамава´нне</Form>
        <Form Tag="GS">анатамава´ння</Form>
        <Form Tag="DS">анатамава´нню</Form>
        <Form Tag="AS">анатамава´нне</Form>
        <Form Tag="IS">анатамава´ннем</Form>
        <Form Tag="LS">анатамава´нні</Form>
    </Paradigm>
    <Paradigm pdgId="0" Lemma="анахрані´чнасць" Tag="NCIINF3">
        <Form Tag="NS">анахрані´чнасць</Form>
        <Form Tag="GS">анахрані´чнасці</Form>
        <Form Tag="DS">анахрані´чнасці</Form>
        <Form Tag="AS">анахрані´чнасць</Form>
        <Form Tag="IS">анахрані´чнасцю</Form>
        <Form Tag="LS">анахрані´чнасці</Form>
    </Paradigm>
    <Paradigm pdgId="0" Lemma="англізава´цца" Tag="VIMR1">
        <Form Tag="0">англізава´цца</Form>
        <Form Tag="R1S">англізу´юся</Form>
        <Form Tag="R2S">англізу´ешся</Form>
        <Form Tag="R3S">англізу´ецца</Form>
        <Form Tag="R1P">англізу´емся</Form>
        <Form Tag="R2P">англізу´ецеся</Form>
        <Form Tag="R3P">англізу´юцца</Form>
        <Form Tag="PXSM">англізава´ўся</Form>
        <Form Tag="PXSF">англізава´лася</Form>
        <Form Tag="PXSN">англізава´лася</Form>
        <Form Tag="PXPX">англізава´ліся</Form>
        <Form Tag="I2S">англізу´йся</Form>
        <Form Tag="I2P">англізу´йцеся</Form>
        <Form Tag="RG">англізу´ючыся</Form>
    </Paradigm>
    <Paradigm pdgId="0" Lemma="англізава´ць" Tag="VTPN1">
        <Form Tag="0">англізава´ць</Form>
        <Form Tag="F1S">англізу´ю</Form>
        <Form Tag="F2S">англізу´еш</Form>
        <Form Tag="F3S">англізу´е</Form>
        <Form Tag="F1P">англізу´ем</Form>
        <Form Tag="F2P">англізу´еце</Form>
        <Form Tag="F3P">англізу´юць</Form>
        <Form Tag="PXSM">англізава´ў</Form>
        <Form Tag="PXSF">англізава´ла</Form>
        <Form Tag="PXSN">англізава´ла</Form>
        <Form Tag="PXPX">англізава´лі</Form>
        <Form Tag="I2S">англізу´й</Form>
        <Form Tag="I2P">англізу´йце</Form>
        <Form Tag="PG">англізава´ўшы</Form>
    </Paradigm>
    <Paradigm pdgId="0" Lemma="англізава´ць" Tag="VTMN1">
        <Form Tag="0">англізава´ць</Form>
        <Form Tag="R1S">англізу´ю</Form>
        <Form Tag="R2S">англізу´еш</Form>
        <Form Tag="R3S">англізу´е</Form>
        <Form Tag="R1P">англізу´ем</Form>
        <Form Tag="R2P">англізу´еце</Form>
        <Form Tag="R3P">англізу´юць</Form>
        <Form Tag="PXSM">англізава´ў</Form>
        <Form Tag="PXSF">англізава´ла</Form>
        <Form Tag="PXSN">англізава´ла</Form>
        <Form Tag="PXPX">англізава´лі</Form>
        <Form Tag="I2S">англізу´й</Form>
        <Form Tag="I2P">англізу´йце</Form>
        <Form Tag="RG">англізу´ючы</Form>
    </Paradigm>
    <Paradigm pdgId="0" Lemma="анекдаты´ст" Tag="NCAPNM1">
        <Form Tag="NS">анекдаты´ст</Form>
        <Form Tag="GS">анекдаты´ста</Form>
        <Form Tag="DS">анекдаты´сту</Form>
        <Form Tag="AS">анекдаты´ста</Form>
        <Form Tag="IS">анекдаты´стам</Form>
        <Form Tag="LS">анекдаты´сце</Form>
        <Form Tag="LS">анекдаты´сту</Form>
        <Form Tag="NP">анекдаты´сты</Form>
        <Form Tag="GP">анекдаты´стаў</Form>
        <Form Tag="DP">анекдаты´стам</Form>
        <Form Tag="AP">анекдаты´стаў</Form>
        <Form Tag="IP">анекдаты´стамі</Form>
        <Form Tag="LP">анекдаты´стах</Form>
    </Paradigm>
    <Paradigm pdgId="0" Lemma="анестэзу´ючы" Tag="ARP">
        <Form Tag="MNS">анестэзу´ючы</Form>
        <Form Tag="MGS">анестэзу´ючага</Form>
        <Form Tag="MDS">анестэзу´ючаму</Form>
        <Form Tag="MAS">анестэзу´ючы</Form>
        <Form Tag="MAS">анестэзу´ючага</Form>
        <Form Tag="MIS">анестэзу´ючым</Form>
        <Form Tag="MLS">анестэзу´ючым</Form>
        <Form Tag="NNS">анестэзу´ючае</Form>
        <Form Tag="NGS">анестэзу´ючага</Form>
        <Form Tag="NDS">анестэзу´ючаму</Form>
        <Form Tag="NAS">анестэзу´ючае</Form>
        <Form Tag="NIS">анестэзу´ючым</Form>
        <Form Tag="NLS">анестэзу´ючым</Form>
        <Form Tag="FNS">анестэзу´ючая</Form>
        <Form Tag="FGS">анестэзу´ючай</Form>
        <Form Tag="FGS">анестэзу´ючае</Form>
        <Form Tag="FDS">анестэзу´ючай</Form>
        <Form Tag="FAS">анестэзу´ючую</Form>
        <Form Tag="FIS">анестэзу´ючай</Form>
        <Form Tag="FIS">анестэзу´ючаю</Form>
        <Form Tag="FLS">анестэзу´ючай</Form>
        <Form Tag="PNP">анестэзу´ючыя</Form>
        <Form Tag="PGP">анестэзу´ючых</Form>
        <Form Tag="PDP">анестэзу´ючым</Form>
        <Form Tag="PAP">анестэзу´ючыя</Form>
        <Form Tag="PIP">анестэзу´ючымі</Form>
        <Form Tag="PLP">анестэзу´ючых</Form>
    </Paradigm>
    <Paradigm pdgId="0" Lemma="анка´рскі" Tag="ARP">
        <Form Tag="MNS">анка´рскі</Form>
        <Form Tag="MGS">анка´рскага</Form>
        <Form Tag="MDS">анка´рскаму</Form>
        <Form Tag="MAS">анка´рскі</Form>
        <Form Tag="MIS">анка´рскім</Form>
        <Form Tag="MLS">анка´рскім</Form>
        <Form Tag="NNS">анка´рскае</Form>
        <Form Tag="NGS">анка´рскага</Form>
        <Form Tag="NDS">анка´рскаму</Form>
        <Form Tag="NAS">анка´рскае</Form>
        <Form Tag="NIS">анка´рскім</Form>
        <Form Tag="NLS">анка´рскім</Form>
        <Form Tag="FNS">анка´рская</Form>
        <Form Tag="FGS">анка´рскай</Form>
        <Form Tag="FGS">анка´рскае</Form>
        <Form Tag="FDS">анка´рскай</Form>
        <Form Tag="FAS">анка´рскую</Form>
        <Form Tag="FIS">анка´рскай</Form>
        <Form Tag="FIS">анка´рскаю</Form>
        <Form Tag="FLS">анка´рскай</Form>
        <Form Tag="PNP">анка´рскія</Form>
        <Form Tag="PGP">анка´рскіх</Form>
        <Form Tag="PDP">анка´рскім</Form>
        <Form Tag="PAP">анка´рскія</Form>
        <Form Tag="PIP">анка´рскімі</Form>
        <Form Tag="PLP">анка´рскіх</Form>
    </Paradigm>
    <Paradigm pdgId="0" Lemma="антагене´зіс" Tag="NCIINM1">
        <Form Tag="NS">антагене´зіс</Form>
        <Form Tag="GS">антагене´зісу</Form>
        <Form Tag="DS">антагене´зісу</Form>
        <Form Tag="AS">антагене´зіс</Form>
        <Form Tag="IS">антагене´зісам</Form>
        <Form Tag="LS">антагене´зісе</Form>
    </Paradigm>
    <Paradigm pdgId="0" Lemma="анто´н" Tag="NCIINM1">
        <Form Tag="NS">анто´н</Form>
        <Form Tag="GS">анто´на</Form>
        <Form Tag="DS">анто´ну</Form>
        <Form Tag="AS">анто´н</Form>
        <Form Tag="IS">анто´нам</Form>
        <Form Tag="LS">анто´не</Form>
        <Form Tag="NP">анто´ны</Form>
        <Form Tag="GP">анто´наў</Form>
        <Form Tag="DP">анто´нам</Form>
        <Form Tag="AP">анто´ны</Form>
        <Form Tag="IP">анто´намі</Form>
        <Form Tag="LP">анто´нах</Form>
    </Paradigm>
    <Paradigm pdgId="0" Lemma="анто´наў" Tag="ARP">
        <Form Tag="MNS">анто´наў</Form>
        <Form Tag="MGS">анто´навага</Form>
        <Form Tag="MDS">анто´наваму</Form>
        <Form Tag="MAS">анто´наў</Form>
        <Form Tag="MAS">анто´навага</Form>
        <Form Tag="MIS">анто´навым</Form>
        <Form Tag="MLS">анто´навым</Form>
        <Form Tag="NNS">анто´нава</Form>
        <Form Tag="NGS">анто´навага</Form>
        <Form Tag="NDS">анто´наваму</Form>
        <Form Tag="NAS">анто´нава</Form>
        <Form Tag="NIS">анто´навым</Form>
        <Form Tag="NLS">анто´навым</Form>
        <Form Tag="FNS">анто´нава</Form>
        <Form Tag="FGS">анто´навай</Form>
        <Form Tag="FGS">анто´навае</Form>
        <Form Tag="FDS">анто´навай</Form>
        <Form Tag="FAS">анто´наву</Form>
        <Form Tag="FIS">анто´навай</Form>
        <Form Tag="FIS">анто´наваю</Form>
        <Form Tag="FLS">анто´навай</Form>
        <Form Tag="PNP">анто´навы</Form>
        <Form Tag="PGP">анто´навых</Form>
        <Form Tag="PDP">анто´навым</Form>
        <Form Tag="PAP">анто´навы</Form>
        <Form Tag="PIP">анто´навымі</Form>
        <Form Tag="PLP">анто´навых</Form>
    </Paradigm>
    <Paradigm pdgId="0" Lemma="антракно´з" Tag="NCIINM1">
        <Form Tag="NS">антракно´з</Form>
        <Form Tag="GS">антракно´зу</Form>
        <Form Tag="DS">антракно´зу</Form>
        <Form Tag="AS">антракно´з</Form>
        <Form Tag="IS">антракно´зам</Form>
        <Form Tag="LS">антракно´зе</Form>
    </Paradigm>
    <Paradigm pdgId="0" Lemma="антрапаге´н" Tag="NCIINM1">
        <Form Tag="NS">антрапаге´н</Form>
        <Form Tag="GS">антрапаге´ну</Form>
        <Form Tag="DS">антрапаге´ну</Form>
        <Form Tag="AS">антрапаге´н</Form>
        <Form Tag="IS">антрапаге´нам</Form>
        <Form Tag="LS">антрапаге´не</Form>
    </Paradigm>
    <Paradigm pdgId="0" Lemma="антыгрыпі´н" Tag="NCIINM1">
        <Form Tag="NS">антыгрыпі´н</Form>
        <Form Tag="GS">антыгрыпі´ну</Form>
        <Form Tag="DS">антыгрыпі´ну</Form>
        <Form Tag="AS">антыгрыпі´н</Form>
        <Form Tag="IS">антыгрыпі´нам</Form>
        <Form Tag="LS">антыгрыпі´не</Form>
    </Paradigm>
    <Paradigm pdgId="0" Lemma="антыкааператы´ўны" Tag="ARP">
        <Form Tag="MNS">антыкааператы´ўны</Form>
        <Form Tag="MGS">антыкааператы´ўнага</Form>
        <Form Tag="MDS">антыкааператы´ўнаму</Form>
        <Form Tag="MAS">антыкааператы´ўны</Form>
        <Form Tag="MAS">антыкааператы´ўнага</Form>
        <Form Tag="MIS">антыкааператы´ўным</Form>
        <Form Tag="MLS">антыкааператы´ўным</Form>
        <Form Tag="NNS">антыкааператы´ўнае</Form>
        <Form Tag="NGS">антыкааператы´ўнага</Form>
        <Form Tag="NDS">антыкааператы´ўнаму</Form>
        <Form Tag="NAS">антыкааператы´ўнае</Form>
        <Form Tag="NIS">антыкааператы´ўным</Form>
        <Form Tag="NLS">антыкааператы´ўным</Form>
        <Form Tag="FNS">антыкааператы´ўная</Form>
        <Form Tag="FGS">антыкааператы´ўнай</Form>
        <Form Tag="FGS">антыкааператы´ўнае</Form>
        <Form Tag="FDS">антыкааператы´ўнай</Form>
        <Form Tag="FAS">антыкааператы´ўную</Form>
        <Form Tag="FIS">антыкааператы´ўнай</Form>
        <Form Tag="FIS">антыкааператы´ўнаю</Form>
        <Form Tag="FLS">антыкааператы´ўнай</Form>
        <Form Tag="PNP">антыкааператы´ўныя</Form>
        <Form Tag="PGP">антыкааператы´ўных</Form>
        <Form Tag="PDP">антыкааператы´ўным</Form>
        <Form Tag="PAP">антыкааператы´ўныя</Form>
        <Form Tag="PIP">антыкааператы´ўнымі</Form>
        <Form Tag="PLP">антыкааператы´ўных</Form>
    </Paradigm>
    <Paradigm pdgId="0" Lemma="антыперабудо´вачны" Tag="AXP">
        <Form Tag="MNS">антыперабудо´вачны</Form>
        <Form Tag="MGS">антыперабудо´вачнага</Form>
        <Form Tag="MDS">антыперабудо´вачнаму</Form>
        <Form Tag="MAS">антыперабудо´вачны</Form>
        <Form Tag="MIS">антыперабудо´вачным</Form>
        <Form Tag="MLS">антыперабудо´вачным</Form>
        <Form Tag="NNS">антыперабудо´вачнае</Form>
        <Form Tag="NGS">антыперабудо´вачнага</Form>
        <Form Tag="NDS">антыперабудо´вачнаму</Form>
        <Form Tag="NAS">антыперабудо´вачнае</Form>
        <Form Tag="NIS">антыперабудо´вачным</Form>
        <Form Tag="NLS">антыперабудо´вачным</Form>
        <Form Tag="FNS">антыперабудо´вачная</Form>
        <Form Tag="FGS">антыперабудо´вачнай</Form>
        <Form Tag="FDS">антыперабудо´вачнай</Form>
        <Form Tag="FAS">антыперабудо´вачную</Form>
        <Form Tag="FIS">антыперабудо´вачнай</Form>
        <Form Tag="FIS">антыперабудо´вачнаю</Form>
        <Form Tag="FLS">антыперабудо´вачнай</Form>
        <Form Tag="PNP">антыперабудо´вачныя</Form>
        <Form Tag="PGP">антыперабудо´вачных</Form>
        <Form Tag="PDP">антыперабудо´вачным</Form>
        <Form Tag="PAP">антыперабудо´вачныя</Form>
        <Form Tag="PIP">антыперабудо´вачнымі</Form>
        <Form Tag="PLP">антыперабудо´вачных</Form>
    </Paradigm>
    <Paradigm pdgId="0" Lemma="антырэвалюцы´йны" Tag="ARP">
        <Form Tag="MNS">антырэвалюцы´йны</Form>
        <Form Tag="MGS">антырэвалюцы´йнага</Form>
        <Form Tag="MDS">антырэвалюцы´йнаму</Form>
        <Form Tag="MAS">антырэвалюцы´йны</Form>
        <Form Tag="MIS">антырэвалюцы´йным</Form>
        <Form Tag="MLS">антырэвалюцы´йным</Form>
        <Form Tag="NNS">антырэвалюцы´йнае</Form>
        <Form Tag="NGS">антырэвалюцы´йнага</Form>
        <Form Tag="NDS">антырэвалюцы´йнаму</Form>
        <Form Tag="NAS">антырэвалюцы´йнае</Form>
        <Form Tag="NIS">антырэвалюцы´йным</Form>
        <Form Tag="NLS">антырэвалюцы´йным</Form>
        <Form Tag="FNS">антырэвалюцы´йная</Form>
        <Form Tag="FGS">антырэвалюцы´йнай</Form>
        <Form Tag="FGS">антырэвалюцы´йнае</Form>
        <Form Tag="FDS">антырэвалюцы´йнай</Form>
        <Form Tag="FAS">антырэвалюцы´йную</Form>
        <Form Tag="FIS">антырэвалюцы´йнай</Form>
        <Form Tag="FIS">антырэвалюцы´йнаю</Form>
        <Form Tag="FLS">антырэвалюцы´йнай</Form>
        <Form Tag="PNP">антырэвалюцы´йныя</Form>
        <Form Tag="PGP">антырэвалюцы´йных</Form>
        <Form Tag="PDP">антырэвалюцы´йным</Form>
        <Form Tag="PAP">антырэвалюцы´йныя</Form>
        <Form Tag="PIP">антырэвалюцы´йнымі</Form>
        <Form Tag="PLP">антырэвалюцы´йных</Form>
    </Paradigm>
    <Paradigm pdgId="0" Lemma="антырэфарма´тар" Tag="NCAPNM1">
        <Form Tag="NS">антырэфарма´тар</Form>
        <Form Tag="GS">антырэфарма´тара</Form>
        <Form Tag="DS">антырэфарма´тару</Form>
        <Form Tag="AS">антырэфарма´тара</Form>
        <Form Tag="IS">антырэфарма´тарам</Form>
        <Form Tag="LS">антырэфарма´тару</Form>
        <Form Tag="NP">антырэфарма´тары</Form>
        <Form Tag="GP">антырэфарма´тараў</Form>
        <Form Tag="DP">антырэфарма´тарам</Form>
        <Form Tag="AP">антырэфарма´тараў</Form>
        <Form Tag="IP">антырэфарма´тарамі</Form>
        <Form Tag="LP">антырэфарма´тарах</Form>
    </Paradigm>
    <Paradigm pdgId="0" Lemma="антысні´давы" Tag="ARP">
        <Form Tag="MNS">антысні´давы</Form>
        <Form Tag="MGS">антысні´давага</Form>
        <Form Tag="MDS">антысні´даваму</Form>
        <Form Tag="MAS">антысні´давы</Form>
        <Form Tag="MAS">антысні´давага</Form>
        <Form Tag="MIS">антысні´давым</Form>
        <Form Tag="MLS">антысні´давым</Form>
        <Form Tag="NNS">антысні´давае</Form>
        <Form Tag="NGS">антысні´давага</Form>
        <Form Tag="NDS">антысні´даваму</Form>
        <Form Tag="NAS">антысні´давае</Form>
        <Form Tag="NIS">антысні´давым</Form>
        <Form Tag="NLS">антысні´давым</Form>
        <Form Tag="FNS">антысні´давая</Form>
        <Form Tag="FGS">антысні´давай</Form>
        <Form Tag="FGS">антысні´давае</Form>
        <Form Tag="FDS">антысні´давай</Form>
        <Form Tag="FAS">антысні´давую</Form>
        <Form Tag="FIS">антысні´давай</Form>
        <Form Tag="FIS">антысні´даваю</Form>
        <Form Tag="FLS">антысні´давай</Form>
        <Form Tag="PNP">антысні´давыя</Form>
        <Form Tag="PGP">антысні´давых</Form>
        <Form Tag="PDP">антысні´давым</Form>
        <Form Tag="PAP">антысні´давыя</Form>
        <Form Tag="PAP">антысні´давых</Form>
        <Form Tag="PIP">антысні´давымі</Form>
        <Form Tag="PLP">антысні´давых</Form>
    </Paradigm>
    <Paradigm pdgId="0" Lemma="антыфебры´н" Tag="NCIINM1">
        <Form Tag="NS">антыфебры´н</Form>
        <Form Tag="GS">антыфебры´ну</Form>
        <Form Tag="DS">антыфебры´ну</Form>
        <Form Tag="AS">антыфебры´н</Form>
        <Form Tag="IS">антыфебры´нам</Form>
        <Form Tag="LS">антыфебры´не</Form>
    </Paradigm>
    <Paradigm pdgId="0" Lemma="антыцыклані´чны" Tag="ARP">
        <Form Tag="MNS">антыцыклані´чны</Form>
        <Form Tag="MGS">антыцыклані´чнага</Form>
        <Form Tag="MDS">антыцыклані´чнаму</Form>
        <Form Tag="MAS">антыцыклані´чны</Form>
        <Form Tag="MIS">антыцыклані´чным</Form>
        <Form Tag="MLS">антыцыклані´чным</Form>
        <Form Tag="NNS">антыцыклані´чнае</Form>
        <Form Tag="NGS">антыцыклані´чнага</Form>
        <Form Tag="NDS">антыцыклані´чнаму</Form>
        <Form Tag="NAS">антыцыклані´чнае</Form>
        <Form Tag="NIS">антыцыклані´чным</Form>
        <Form Tag="NLS">антыцыклані´чным</Form>
        <Form Tag="FNS">антыцыклані´чная</Form>
        <Form Tag="FGS">антыцыклані´чнай</Form>
        <Form Tag="FGS">антыцыклані´чнае</Form>
        <Form Tag="FDS">антыцыклані´чнай</Form>
        <Form Tag="FAS">антыцыклані´чную</Form>
        <Form Tag="FIS">антыцыклані´чнай</Form>
        <Form Tag="FIS">антыцыклані´чнаю</Form>
        <Form Tag="FLS">антыцыклані´чнай</Form>
        <Form Tag="PNP">антыцыклані´чныя</Form>
        <Form Tag="PGP">антыцыклані´чных</Form>
        <Form Tag="PDP">антыцыклані´чным</Form>
        <Form Tag="PAP">антыцыклані´чныя</Form>
        <Form Tag="PIP">антыцыклані´чнымі</Form>
        <Form Tag="PLP">антыцыклані´чных</Form>
    </Paradigm>
    <Paradigm pdgId="0" Lemma="анё´р" Tag="NCIINM1" options="usually_plurals">
        <Form Tag="NS">анё´р</Form>
        <Form Tag="GS">анё´ра</Form>
        <Form Tag="DS">анё´ру</Form>
        <Form Tag="AS">анё´р</Form>
        <Form Tag="IS">анё´рам</Form>
        <Form Tag="LS">анё´ры</Form>
        <Form Tag="NP">анё´ры</Form>
        <Form Tag="GP">анё´раў</Form>
        <Form Tag="DP">анё´рам</Form>
        <Form Tag="AP">анё´ры</Form>
        <Form Tag="IP">анё´рамі</Form>
        <Form Tag="LP">анё´рах</Form>
    </Paradigm>
    <Paradigm pdgId="0" Lemma="аніба´лаў" Tag="ARP">
        <Form Tag="MNS">аніба´лаў</Form>
        <Form Tag="MGS">аніба´лавага</Form>
        <Form Tag="MDS">аніба´лаваму</Form>
        <Form Tag="MAS">аніба´лаў</Form>
        <Form Tag="MAS">аніба´лавага</Form>
        <Form Tag="MIS">аніба´лавым</Form>
        <Form Tag="MLS">аніба´лавым</Form>
        <Form Tag="NNS">аніба´лава</Form>
        <Form Tag="NGS">аніба´лавага</Form>
        <Form Tag="NDS">аніба´лаваму</Form>
        <Form Tag="NAS">аніба´лава</Form>
        <Form Tag="NIS">аніба´лавым</Form>
        <Form Tag="NLS">аніба´лавым</Form>
        <Form Tag="FNS">аніба´лава</Form>
        <Form Tag="FGS">аніба´лавай</Form>
        <Form Tag="FGS">аніба´лавае</Form>
        <Form Tag="FDS">аніба´лавай</Form>
        <Form Tag="FAS">аніба´лаву</Form>
        <Form Tag="FIS">аніба´лавай</Form>
        <Form Tag="FIS">аніба´лаваю</Form>
        <Form Tag="FLS">аніба´лавай</Form>
        <Form Tag="PNP">аніба´лавы</Form>
        <Form Tag="PGP">аніба´лавых</Form>
        <Form Tag="PDP">аніба´лавым</Form>
        <Form Tag="PAP">аніба´лавы</Form>
        <Form Tag="PIP">аніба´лавымі</Form>
        <Form Tag="PLP">аніба´лавых</Form>
    </Paradigm>
    <Paradigm pdgId="0" Lemma="апа´мятавацца" Tag="VIPR1">
        <Form Tag="0">апа´мятавацца</Form>
        <Form Tag="F1S">апа´мятуюся</Form>
        <Form Tag="F2S">апа´мятуешся</Form>
        <Form Tag="F3S">апа´мятуецца</Form>
        <Form Tag="F1P">апа´мятуемся</Form>
        <Form Tag="F2P">апа´мятуецеся</Form>
        <Form Tag="F3P">апа´мятуюцца</Form>
        <Form Tag="PXSM">апа´мятаваўся</Form>
        <Form Tag="PXSF">апа´мятавалася</Form>
        <Form Tag="PXSN">апа´мятавалася</Form>
        <Form Tag="PXPX">апа´мятаваліся</Form>
        <Form Tag="I2S">апа´мятуйся</Form>
        <Form Tag="I2P">апа´мятуйцеся</Form>
        <Form Tag="PG">апа´мятаваўшыся</Form>
    </Paradigm>
    <Paradigm pdgId="0" Lemma="апары´я" Tag="NCIINF2">
        <Form Tag="NS">апары´я</Form>
        <Form Tag="GS">апары´і</Form>
        <Form Tag="DS">апары´і</Form>
        <Form Tag="AS">апары´ю</Form>
        <Form Tag="IS">апары´яй</Form>
        <Form Tag="IS">апары´яю</Form>
        <Form Tag="LS">апары´і</Form>
        <Form Tag="NP">апары´і</Form>
        <Form Tag="GP">апары´й</Form>
        <Form Tag="DP">апары´ям</Form>
        <Form Tag="AP">апары´і</Form>
        <Form Tag="IP">апары´ямі</Form>
        <Form Tag="LP">апары´ях</Form>
    </Paradigm>
    <Paradigm pdgId="0" Lemma="апаса´цца" Tag="VIMR1">
        <Form Tag="0">апаса´цца</Form>
        <Form Tag="R1S">апаса´юся</Form>
        <Form Tag="R2S">апаса´ешся</Form>
        <Form Tag="R3S">апаса´ецца</Form>
        <Form Tag="R1P">апаса´емся</Form>
        <Form Tag="R2P">апаса´ецеся</Form>
        <Form Tag="R3P">апаса´юцца</Form>
        <Form Tag="PXSM">апаса´ўся</Form>
        <Form Tag="PXSF">апаса´лася</Form>
        <Form Tag="PXSN">апаса´лася</Form>
        <Form Tag="PXPX">апаса´ліся</Form>
        <Form Tag="I2S">апаса´йся</Form>
        <Form Tag="I2P">апаса´йцеся</Form>
        <Form Tag="RG">апаса´ючыся</Form>
    </Paradigm>
    <Paradigm pdgId="0" Lemma="апатры´д" Tag="NCAPNM1">
        <Form Tag="NS">апатры´д</Form>
        <Form Tag="GS">апатры´да</Form>
        <Form Tag="DS">апатры´ду</Form>
        <Form Tag="AS">апатры´да</Form>
        <Form Tag="IS">апатры´дам</Form>
        <Form Tag="LS">апатры´дзе</Form>
        <Form Tag="NP">апатры´ды</Form>
        <Form Tag="GP">апатры´даў</Form>
        <Form Tag="DP">апатры´дам</Form>
        <Form Tag="AP">апатры´даў</Form>
        <Form Tag="IP">апатры´дамі</Form>
        <Form Tag="LP">апатры´дах</Form>
    </Paradigm>
    <Paradigm pdgId="0" Lemma="апафе´гма" Tag="NCIINF2">
        <Form Tag="NS">апафе´гма</Form>
        <Form Tag="GS">апафе´гмы</Form>
        <Form Tag="DS">апафе´гме</Form>
        <Form Tag="AS">апафе´гму</Form>
        <Form Tag="IS">апафе´гмай</Form>
        <Form Tag="IS">апафе´гмаю</Form>
        <Form Tag="LS">апафе´гме</Form>
        <Form Tag="NP">апафе´гмы</Form>
        <Form Tag="GP">апафе´гм</Form>
        <Form Tag="DP">апафе´гмам</Form>
        <Form Tag="AP">апафе´гмы</Form>
        <Form Tag="IP">апафе´гмамі</Form>
        <Form Tag="LP">апафе´гмах</Form>
    </Paradigm>
    <Paradigm pdgId="0" Lemma="апаферме´нт" Tag="NCIINM1">
        <Form Tag="NS">апаферме´нт</Form>
        <Form Tag="GS">апаферме´нту</Form>
        <Form Tag="DS">апаферме´нту</Form>
        <Form Tag="AS">апаферме´нт</Form>
        <Form Tag="IS">апаферме´нтам</Form>
        <Form Tag="LS">апаферме´нце</Form>
        <Form Tag="NP">апаферме´нты</Form>
        <Form Tag="GP">апаферме´нтаў</Form>
        <Form Tag="DP">апаферме´нтам</Form>
        <Form Tag="AP">апаферме´нты</Form>
        <Form Tag="IP">апаферме´нтамі</Form>
        <Form Tag="LP">апаферме´нтах</Form>
    </Paradigm>
    <Paradigm pdgId="0" Lemma="апашэ´нь" Tag="NCIINM1">
        <Form Tag="NS">апашэ´нь</Form>
        <Form Tag="GS">апашня´</Form>
        <Form Tag="DS">апашню´</Form>
        <Form Tag="AS">апашэ´нь</Form>
        <Form Tag="IS">апашнё´м</Form>
        <Form Tag="LS">апашні´</Form>
        <Form Tag="NP">апашні´</Form>
        <Form Tag="GP">апашнё´ў</Form>
        <Form Tag="DP">апашням</Form>
        <Form Tag="AP">апашні´</Form>
        <Form Tag="IP">апашня´мі</Form>
        <Form Tag="LP">апашня´х</Form>
    </Paradigm>
    <Paradigm pdgId="0" Lemma="апаўдня´" Tag="RX">
        <Form Tag="P">апаўдня´</Form>
    </Paradigm>
    <Paradigm pdgId="0" Lemma="апе´рваць" Tag="VTMN1">
        <Form Tag="0">апе´рваць</Form>
        <Form Tag="R1S">апе´рваю</Form>
        <Form Tag="R2S">апе´рваеш</Form>
        <Form Tag="R3S">апе´рвае</Form>
        <Form Tag="R1P">апе´рваем</Form>
        <Form Tag="R2P">апе´рваеце</Form>
        <Form Tag="R3P">апе´рваюць</Form>
        <Form Tag="PXSM">апе´рваў</Form>
        <Form Tag="PXSF">апе´рвала</Form>
        <Form Tag="PXSN">апе´рвала</Form>
        <Form Tag="PXPX">апе´рвалі</Form>
        <Form Tag="I2S">апе´рвай</Form>
        <Form Tag="I2P">апе´рвайце</Form>
        <Form Tag="RG">апе´рваючы</Form>
    </Paradigm>
    <Paradigm pdgId="0" Lemma="апелі´раваць" Tag="VTMN1">
        <Form Tag="0">апелі´раваць</Form>
        <Form Tag="R1S">апелі´рую</Form>
        <Form Tag="R2S">апелі´руеш</Form>
        <Form Tag="R3S">апелі´руе</Form>
        <Form Tag="R1P">апелі´руем</Form>
        <Form Tag="R2P">апелі´руеце</Form>
        <Form Tag="R3P">апелі´руюць</Form>
        <Form Tag="PXSM">апелі´раваў</Form>
        <Form Tag="PXSF">апелі´равала</Form>
        <Form Tag="PXSN">апелі´равала</Form>
        <Form Tag="PXPX">апелі´равалі</Form>
        <Form Tag="I2S">апелі´руй</Form>
        <Form Tag="I2P">апелі´руйце</Form>
        <Form Tag="RG">апелі´руючы</Form>
    </Paradigm>
    <Paradigm pdgId="0" Lemma="аператы´ўна-вытво´рчы" Tag="ARP">
        <Form Tag="MNS">аператы´ўна-вытво´рчы</Form>
        <Form Tag="MGS">аператы´ўна-вытво´рчага</Form>
        <Form Tag="MDS">аператы´ўна-вытво´рчаму</Form>
        <Form Tag="MAS">аператы´ўна-вытво´рчы</Form>
        <Form Tag="MAS">аператы´ўна-вытво´рчага</Form>
        <Form Tag="MIS">аператы´ўна-вытво´рчым</Form>
        <Form Tag="MLS">аператы´ўна-вытво´рчым</Form>
        <Form Tag="NNS">аператы´ўна-вытво´рчае</Form>
        <Form Tag="NGS">аператы´ўна-вытво´рчага</Form>
        <Form Tag="NDS">аператы´ўна-вытво´рчаму</Form>
        <Form Tag="NAS">аператы´ўна-вытво´рчае</Form>
        <Form Tag="NIS">аператы´ўна-вытво´рчым</Form>
        <Form Tag="NLS">аператы´ўна-вытво´рчым</Form>
        <Form Tag="FNS">аператы´ўна-вытво´рчая</Form>
        <Form Tag="FGS">аператы´ўна-вытво´рчай</Form>
        <Form Tag="FGS">аператы´ўна-вытво´рчае</Form>
        <Form Tag="FDS">аператы´ўна-вытво´рчай</Form>
        <Form Tag="FAS">аператы´ўна-вытво´рчую</Form>
        <Form Tag="FIS">аператы´ўна-вытво´рчай</Form>
        <Form Tag="FIS">аператы´ўна-вытво´рчаю</Form>
        <Form Tag="FLS">аператы´ўна-вытво´рчай</Form>
        <Form Tag="PNP">аператы´ўна-вытво´рчыя</Form>
        <Form Tag="PGP">аператы´ўна-вытво´рчых</Form>
        <Form Tag="PDP">аператы´ўна-вытво´рчым</Form>
        <Form Tag="PAP">аператы´ўна-вытво´рчыя</Form>
        <Form Tag="PIP">аператы´ўна-вытво´рчымі</Form>
        <Form Tag="PLP">аператы´ўна-вытво´рчых</Form>
    </Paradigm>
    <Paradigm pdgId="0" Lemma="аператы´ўна-кантро´льны" Tag="ARP">
        <Form Tag="MNS">аператы´ўна-кантро´льны</Form>
        <Form Tag="MGS">аператы´ўна-кантро´льнага</Form>
        <Form Tag="MDS">аператы´ўна-кантро´льнаму</Form>
        <Form Tag="MAS">аператы´ўна-кантро´льны</Form>
        <Form Tag="MAS">аператы´ўна-кантро´льнага</Form>
        <Form Tag="MIS">аператы´ўна-кантро´льным</Form>
        <Form Tag="MLS">аператы´ўна-кантро´льным</Form>
        <Form Tag="NNS">аператы´ўна-кантро´льнае</Form>
        <Form Tag="NGS">аператы´ўна-кантро´льнага</Form>
        <Form Tag="NDS">аператы´ўна-кантро´льнаму</Form>
        <Form Tag="NAS">аператы´ўна-кантро´льнае</Form>
        <Form Tag="NIS">аператы´ўна-кантро´льным</Form>
        <Form Tag="NLS">аператы´ўна-кантро´льным</Form>
        <Form Tag="FNS">аператы´ўна-кантро´льная</Form>
        <Form Tag="FGS">аператы´ўна-кантро´льнай</Form>
        <Form Tag="FGS">аператы´ўна-кантро´льнае</Form>
        <Form Tag="FDS">аператы´ўна-кантро´льнай</Form>
        <Form Tag="FAS">аператы´ўна-кантро´льную</Form>
        <Form Tag="FIS">аператы´ўна-кантро´льнай</Form>
        <Form Tag="FIS">аператы´ўна-кантро´льнаю</Form>
        <Form Tag="FLS">аператы´ўна-кантро´льнай</Form>
        <Form Tag="PNP">аператы´ўна-кантро´льныя</Form>
        <Form Tag="PGP">аператы´ўна-кантро´льных</Form>
        <Form Tag="PDP">аператы´ўна-кантро´льным</Form>
        <Form Tag="PAP">аператы´ўна-кантро´льныя</Form>
        <Form Tag="PIP">аператы´ўна-кантро´льнымі</Form>
        <Form Tag="PLP">аператы´ўна-кантро´льных</Form>
    </Paradigm>
    <Paradigm pdgId="0" Lemma="аператы´ўна-стратэгі´чны" Tag="ARP">
        <Form Tag="MNS">аператы´ўна-стратэгі´чны</Form>
        <Form Tag="MGS">аператы´ўна-стратэгі´чнага</Form>
        <Form Tag="MDS">аператы´ўна-стратэгі´чнаму</Form>
        <Form Tag="MAS">аператы´ўна-стратэгі´чны</Form>
        <Form Tag="MAS">аператы´ўна-стратэгі´чнага</Form>
        <Form Tag="MIS">аператы´ўна-стратэгі´чным</Form>
        <Form Tag="MLS">аператы´ўна-стратэгі´чным</Form>
        <Form Tag="NNS">аператы´ўна-стратэгі´чнае</Form>
        <Form Tag="NGS">аператы´ўна-стратэгі´чнага</Form>
        <Form Tag="NDS">аператы´ўна-стратэгі´чнаму</Form>
        <Form Tag="NAS">аператы´ўна-стратэгі´чнае</Form>
        <Form Tag="NIS">аператы´ўна-стратэгі´чным</Form>
        <Form Tag="NLS">аператы´ўна-стратэгі´чным</Form>
        <Form Tag="FNS">аператы´ўна-стратэгі´чная</Form>
        <Form Tag="FGS">аператы´ўна-стратэгі´чнай</Form>
        <Form Tag="FGS">аператы´ўна-стратэгі´чнае</Form>
        <Form Tag="FDS">аператы´ўна-стратэгі´чнай</Form>
        <Form Tag="FAS">аператы´ўна-стратэгі´чную</Form>
        <Form Tag="FIS">аператы´ўна-стратэгі´чнай</Form>
        <Form Tag="FIS">аператы´ўна-стратэгі´чнаю</Form>
        <Form Tag="FLS">аператы´ўна-стратэгі´чнай</Form>
        <Form Tag="PNP">аператы´ўна-стратэгі´чныя</Form>
        <Form Tag="PGP">аператы´ўна-стратэгі´чных</Form>
        <Form Tag="PDP">аператы´ўна-стратэгі´чным</Form>
        <Form Tag="PAP">аператы´ўна-стратэгі´чныя</Form>
        <Form Tag="PIP">аператы´ўна-стратэгі´чнымі</Form>
        <Form Tag="PLP">аператы´ўна-стратэгі´чных</Form>
    </Paradigm>
    <Paradigm pdgId="0" Lemma="аператы´ўна-хірургічны" Tag="ARP">
        <Form Tag="MNS">аператы´ўна-хірургі´чны</Form>
        <Form Tag="MGS">аператы´ўна-хірургі´чнага</Form>
        <Form Tag="MDS">аператы´ўна-хірургі´чнаму</Form>
        <Form Tag="MAS">аператы´ўна-хірургі´чны</Form>
        <Form Tag="MAS">аператы´ўна-хірургі´чнага</Form>
        <Form Tag="MIS">аператы´ўна-хірургі´чным</Form>
        <Form Tag="MLS">аператы´ўна-хірургі´чным</Form>
        <Form Tag="NNS">аператы´ўна-хірургі´чнае</Form>
        <Form Tag="NGS">аператы´ўна-хірургі´чнага</Form>
        <Form Tag="NDS">аператы´ўна-хірургі´чнаму</Form>
        <Form Tag="NAS">аператы´ўна-хірургі´чнае</Form>
        <Form Tag="NIS">аператы´ўна-хірургі´чным</Form>
        <Form Tag="NLS">аператы´ўна-хірургі´чным</Form>
        <Form Tag="FNS">аператы´ўна-хірургі´чная</Form>
        <Form Tag="FGS">аператы´ўна-хірургі´чнай</Form>
        <Form Tag="FGS">аператы´ўна-хірургі´чнае</Form>
        <Form Tag="FDS">аператы´ўна-хірургі´чнай</Form>
        <Form Tag="FAS">аператы´ўна-хірургі´чную</Form>
        <Form Tag="FIS">аператы´ўна-хірургі´чнай</Form>
        <Form Tag="FIS">аператы´ўна-хірургі´чнаю</Form>
        <Form Tag="FLS">аператы´ўна-хірургі´чнай</Form>
        <Form Tag="PNP">аператы´ўна-хірургі´чныя</Form>
        <Form Tag="PGP">аператы´ўна-хірургі´чных</Form>
        <Form Tag="PDP">аператы´ўна-хірургі´чным</Form>
        <Form Tag="PAP">аператы´ўна-хірургі´чныя</Form>
        <Form Tag="PIP">аператы´ўна-хірургі´чнымі</Form>
        <Form Tag="PLP">аператы´ўна-хірургі´чных</Form>
    </Paradigm>
    <Paradigm pdgId="0" Lemma="аплява´цца" Tag="VIPR1">
        <Form Tag="0">аплява´цца</Form>
        <Form Tag="F1S">аплюю´ся</Form>
        <Form Tag="F2S">аплюе´шся</Form>
        <Form Tag="F3S">аплюе´цца</Form>
        <Form Tag="F1P">аплюе´мся</Form>
        <Form Tag="F1P">аплюё´мся</Form>
        <Form Tag="F2P">аплюе´цеся</Form>
        <Form Tag="F2P">аплюяце´ся</Form>
        <Form Tag="F3P">аплюю´цца</Form>
        <Form Tag="PXSM">аплява´ўся</Form>
        <Form Tag="PXSF">аплява´лася</Form>
        <Form Tag="PXSN">аплява´лася</Form>
        <Form Tag="PXPX">аплява´ліся</Form>
        <Form Tag="I2S">аплю´йся</Form>
        <Form Tag="I2P">аплю´йцеся</Form>
        <Form Tag="PG">аплява´ўшыся</Form>
    </Paradigm>
    <Paradigm pdgId="0" Lemma="апо´рна-паказа´льны" Tag="ARP">
        <Form Tag="MNS">апо´рна-паказа´льны</Form>
        <Form Tag="MGS">апо´рна-паказа´льнага</Form>
        <Form Tag="MDS">апо´рна-паказа´льнаму</Form>
        <Form Tag="MAS">апо´рна-паказа´льны</Form>
        <Form Tag="MAS">апо´рна-паказа´льнага</Form>
        <Form Tag="MIS">апо´рна-паказа´льным</Form>
        <Form Tag="MLS">апо´рна-паказа´льным</Form>
        <Form Tag="NNS">апо´рна-паказа´льнае</Form>
        <Form Tag="NGS">апо´рна-паказа´льнага</Form>
        <Form Tag="NDS">апо´рна-паказа´льнаму</Form>
        <Form Tag="NAS">апо´рна-паказа´льнае</Form>
        <Form Tag="NIS">апо´рна-паказа´льным</Form>
        <Form Tag="NLS">апо´рна-паказа´льным</Form>
        <Form Tag="FNS">апо´рна-паказа´льная</Form>
        <Form Tag="FGS">апо´рна-паказа´льнай</Form>
        <Form Tag="FGS">апо´рна-паказа´льнае</Form>
        <Form Tag="FDS">апо´рна-паказа´льнай</Form>
        <Form Tag="FAS">апо´рна-паказа´льную</Form>
        <Form Tag="FIS">апо´рна-паказа´льнай</Form>
        <Form Tag="FIS">апо´рна-паказа´льнаю</Form>
        <Form Tag="FLS">апо´рна-паказа´льнай</Form>
        <Form Tag="PNP">апо´рна-паказа´льныя</Form>
        <Form Tag="PGP">апо´рна-паказа´льных</Form>
        <Form Tag="PDP">апо´рна-паказа´льным</Form>
        <Form Tag="PAP">апо´рна-паказа´льныя</Form>
        <Form Tag="PIP">апо´рна-паказа´льнымі</Form>
        <Form Tag="PLP">апо´рна-паказа´льных</Form>
    </Paradigm>
    <Paradigm pdgId="0" Lemma="апо´ўдня" Tag="RX">
        <Form Tag="P">апо´ўдня</Form>
    </Paradigm>
    <Paradigm pdgId="0" Lemma="апрана´льня" Tag="NCIINF2">
        <Form Tag="NS">апрана´льня</Form>
        <Form Tag="GS">апрана´льні</Form>
        <Form Tag="DS">апрана´льні</Form>
        <Form Tag="AS">апрана´льню</Form>
        <Form Tag="IS">апрана´льняй</Form>
        <Form Tag="IS">апрана´льняю</Form>
        <Form Tag="LS">апрана´льні</Form>
        <Form Tag="NP">апрана´льні</Form>
        <Form Tag="GP">апрана´льняў</Form>
        <Form Tag="DP">апрана´льням</Form>
        <Form Tag="AP">апрана´льні</Form>
        <Form Tag="IP">апрана´льнямі</Form>
        <Form Tag="LP">апрана´льнях</Form>
    </Paradigm>
    <Paradigm pdgId="0" Lemma="апрасо´ваны" Tag="PPPP">
        <Form Tag="MNS">апрасо´ваны</Form>
        <Form Tag="MGS">апрасо´ванага</Form>
        <Form Tag="MDS">апрасо´ванаму</Form>
        <Form Tag="MAS">апрасо´ваны</Form>
        <Form Tag="MAS">апрасо´ванага</Form>
        <Form Tag="MIS">апрасо´ваным</Form>
        <Form Tag="MLS">апрасо´ваным</Form>
        <Form Tag="NNS">апрасо´ванае</Form>
        <Form Tag="NGS">апрасо´ванага</Form>
        <Form Tag="NDS">апрасо´ванаму</Form>
        <Form Tag="NAS">апрасо´ванае</Form>
        <Form Tag="NIS">апрасо´ваным</Form>
        <Form Tag="NLS">апрасо´ваным</Form>
        <Form Tag="FNS">апрасо´ваная</Form>
        <Form Tag="FGS">апрасо´ванай</Form>
        <Form Tag="FGS">апрасо´ванае</Form>
        <Form Tag="FDS">апрасо´ванай</Form>
        <Form Tag="FAS">апрасо´ваную</Form>
        <Form Tag="FIS">апрасо´ванай</Form>
        <Form Tag="FIS">апрасо´ванаю</Form>
        <Form Tag="FLS">апрасо´ванай</Form>
        <Form Tag="PNP">апрасо´ваныя</Form>
        <Form Tag="PGP">апрасо´ваных</Form>
        <Form Tag="PDP">апрасо´ваным</Form>
        <Form Tag="PAP">апрасо´ваныя</Form>
        <Form Tag="PAP">апрасо´ваных</Form>
        <Form Tag="PIP">апрасо´ванымі</Form>
        <Form Tag="PLP">апрасо´ваных</Form>
    </Paradigm>
    <Paradigm pdgId="0" Lemma="апратэсто´ваны" Tag="PPPP">
        <Form Tag="MNS">апратэсто´ваны</Form>
        <Form Tag="MGS">апратэсто´ванага</Form>
        <Form Tag="MDS">апратэсто´ванаму</Form>
        <Form Tag="MAS">апратэсто´ваны</Form>
        <Form Tag="MAS">апратэсто´ванага</Form>
        <Form Tag="MIS">апратэсто´ваным</Form>
        <Form Tag="MLS">апратэсто´ваным</Form>
        <Form Tag="NNS">апратэсто´ванае</Form>
        <Form Tag="NGS">апратэсто´ванага</Form>
        <Form Tag="NDS">апратэсто´ванаму</Form>
        <Form Tag="NAS">апратэсто´ванае</Form>
        <Form Tag="NIS">апратэсто´ваным</Form>
        <Form Tag="NLS">апратэсто´ваным</Form>
        <Form Tag="FNS">апратэсто´ваная</Form>
        <Form Tag="FGS">апратэсто´ванай</Form>
        <Form Tag="FGS">апратэсто´ванае</Form>
        <Form Tag="FDS">апратэсто´ванай</Form>
        <Form Tag="FAS">апратэсто´ваную</Form>
        <Form Tag="FIS">апратэсто´ванай</Form>
        <Form Tag="FIS">апратэсто´ванаю</Form>
        <Form Tag="FLS">апратэсто´ванай</Form>
        <Form Tag="PNP">апратэсто´ваныя</Form>
        <Form Tag="PGP">апратэсто´ваных</Form>
        <Form Tag="PDP">апратэсто´ваным</Form>
        <Form Tag="PAP">апратэсто´ваныя</Form>
        <Form Tag="PAP">апратэсто´ваных</Form>
        <Form Tag="PIP">апратэсто´ванымі</Form>
        <Form Tag="PLP">апратэсто´ваных</Form>
    </Paradigm>
    <Paradigm pdgId="0" Lemma="апратэсто´ваны" Tag="ARP">
        <Form Tag="MNS">апратэсто´ваны</Form>
        <Form Tag="MGS">апратэсто´ванага</Form>
        <Form Tag="MDS">апратэсто´ванаму</Form>
        <Form Tag="MAS">апратэсто´ваны</Form>
        <Form Tag="MAS">апратэсто´ванага</Form>
        <Form Tag="MIS">апратэсто´ваным</Form>
        <Form Tag="MLS">апратэсто´ваным</Form>
        <Form Tag="NNS">апратэсто´ванае</Form>
        <Form Tag="NGS">апратэсто´ванага</Form>
        <Form Tag="NDS">апратэсто´ванаму</Form>
        <Form Tag="NAS">апратэсто´ванае</Form>
        <Form Tag="NIS">апратэсто´ваным</Form>
        <Form Tag="NLS">апратэсто´ваным</Form>
        <Form Tag="FNS">апратэсто´ваная</Form>
        <Form Tag="FGS">апратэсто´ванай</Form>
        <Form Tag="FGS">апратэсто´ванае</Form>
        <Form Tag="FDS">апратэсто´ванай</Form>
        <Form Tag="FAS">апратэсто´ваную</Form>
        <Form Tag="FIS">апратэсто´ванай</Form>
        <Form Tag="FIS">апратэсто´ванаю</Form>
        <Form Tag="FLS">апратэсто´ванай</Form>
        <Form Tag="PNP">апратэсто´ваныя</Form>
        <Form Tag="PGP">апратэсто´ваных</Form>
        <Form Tag="PDP">апратэсто´ваным</Form>
        <Form Tag="PAP">апратэсто´ваныя</Form>
        <Form Tag="PIP">апратэсто´ванымі</Form>
        <Form Tag="PLP">апратэсто´ваных</Form>
    </Paradigm>
    <Paradigm pdgId="0" Lemma="апрэці´раванне" Tag="NCIINN1">
        <Form Tag="NS">апрэці´раванне</Form>
        <Form Tag="GS">апрэці´равання</Form>
        <Form Tag="DS">апрэці´раванню</Form>
        <Form Tag="AS">апрэці´раванне</Form>
        <Form Tag="IS">апрэці´раваннем</Form>
        <Form Tag="LS">апрэці´раванні</Form>
    </Paradigm>
    <Paradigm pdgId="0" Lemma="апрэці´равацца" Tag="VIMR1">
        <Form Tag="0">апрэці´равацца</Form>
        <Form Tag="R1S" Type="potential">апрэці´руюся</Form>
        <Form Tag="R2S" Type="potential">апрэці´руешся</Form>
        <Form Tag="R3S">апрэці´руецца</Form>
        <Form Tag="R1P" Type="potential">апрэці´руемся</Form>
        <Form Tag="R2P" Type="potential">апрэці´руецеся</Form>
        <Form Tag="R3P">апрэці´руюцца</Form>
        <Form Tag="PXSM">апрэці´раваўся</Form>
        <Form Tag="PXSF">апрэці´равалася</Form>
        <Form Tag="PXSN">апрэці´равалася</Form>
        <Form Tag="PXPX">апрэці´раваліся</Form>
        <Form Tag="I2S" Type="potential">апрэці´руйся</Form>
        <Form Tag="I2P" Type="potential">апрэці´руйцеся</Form>
        <Form Tag="RG">апрэці´руючыся</Form>
    </Paradigm>
    <Paradigm pdgId="0" Lemma="апрэці´раваць" Tag="VTMN1">
        <Form Tag="0">апрэці´раваць</Form>
        <Form Tag="R1S">апрэці´рую</Form>
        <Form Tag="R2S">апрэці´руеш</Form>
        <Form Tag="R3S">апрэці´руе</Form>
        <Form Tag="R1P">апрэці´руем</Form>
        <Form Tag="R2P">апрэці´руеце</Form>
        <Form Tag="R3P">апрэці´руюць</Form>
        <Form Tag="PXSM">апрэці´раваў</Form>
        <Form Tag="PXSF">апрэці´равала</Form>
        <Form Tag="PXSN">апрэці´равала</Form>
        <Form Tag="PXPX">апрэці´равалі</Form>
        <Form Tag="I2S">апрэці´руй</Form>
        <Form Tag="I2P">апрэці´руйце</Form>
        <Form Tag="RG">апрэці´руючы</Form>
    </Paradigm>
    <Paradigm pdgId="0" Lemma="апрэці´раваць" Tag="VTPN1">
        <Form Tag="0">апрэці´раваць</Form>
        <Form Tag="F1S">апрэці´рую</Form>
        <Form Tag="F2S">апрэці´руеш</Form>
        <Form Tag="F3S">апрэці´руе</Form>
        <Form Tag="F1P">апрэці´руем</Form>
        <Form Tag="F2P">апрэці´руеце</Form>
        <Form Tag="F3P">апрэці´руюць</Form>
        <Form Tag="PXSM">апрэці´раваў</Form>
        <Form Tag="PXSF">апрэці´равала</Form>
        <Form Tag="PXSN">апрэці´равала</Form>
        <Form Tag="PXPX">апрэці´равалі</Form>
        <Form Tag="I2S">апрэці´руй</Form>
        <Form Tag="I2P">апрэці´руйце</Form>
        <Form Tag="PG">апрэці´раваўшы</Form>
    </Paradigm>
    <Paradigm pdgId="0" Lemma="аптэ´карыха" Tag="NCAPNF2">
        <Form Tag="NS">аптэ´карыха</Form>
        <Form Tag="GS">аптэ´карыхі</Form>
        <Form Tag="DS">аптэ´карысе</Form>
        <Form Tag="AS">аптэ´карыху</Form>
        <Form Tag="IS">аптэ´карыхай</Form>
        <Form Tag="IS">аптэ´карыхаю</Form>
        <Form Tag="LS">аптэ´карысе</Form>
        <Form Tag="NP">аптэ´карыхі</Form>
        <Form Tag="GP">аптэ´карых</Form>
        <Form Tag="DP">аптэ´карыхам</Form>
        <Form Tag="AP">аптэ´карых</Form>
        <Form Tag="IP">аптэ´карыхамі</Form>
        <Form Tag="LP">аптэ´карыхах</Form>
    </Paradigm>
    <Paradigm pdgId="0" Lemma="апыні´цца" Tag="VIPR2">
        <Form Tag="0">апыні´цца</Form>
        <Form Tag="F1S">апыню´ся</Form>
        <Form Tag="F2S">апы´нішся</Form>
        <Form Tag="F3S">апы´ніцца</Form>
        <Form Tag="F1P">апы´німся</Form>
        <Form Tag="F2P">апы´ніцеся</Form>
        <Form Tag="F3P">апы´няцца</Form>
        <Form Tag="PXSM">апыні´ўся</Form>
        <Form Tag="PXSF">апыні´лася</Form>
        <Form Tag="PXSN">апыні´лася</Form>
        <Form Tag="PXPX">апыні´ліся</Form>
        <Form Tag="I2S">апыні´ся</Form>
        <Form Tag="I2P">апыні´цеся</Form>
        <Form Tag="PG">апыні´ўшыся</Form>
    </Paradigm>
    <Paradigm pdgId="0" Lemma="арабе´сачны" Tag="ARP">
        <Form Tag="MNS">арабе´сачны</Form>
        <Form Tag="MGS">арабе´сачнага</Form>
        <Form Tag="MDS">арабе´сачнаму</Form>
        <Form Tag="MAS">арабе´сачны</Form>
        <Form Tag="MIS">арабе´сачным</Form>
        <Form Tag="MLS">арабе´сачным</Form>
        <Form Tag="NNS">арабе´сачнае</Form>
        <Form Tag="NGS">арабе´сачнага</Form>
        <Form Tag="NDS">арабе´сачнаму</Form>
        <Form Tag="NAS">арабе´сачнае</Form>
        <Form Tag="NIS">арабе´сачным</Form>
        <Form Tag="NLS">арабе´сачным</Form>
        <Form Tag="FNS">арабе´сачная</Form>
        <Form Tag="FGS">арабе´сачнай</Form>
        <Form Tag="FGS">арабе´сачнае</Form>
        <Form Tag="FDS">арабе´сачнай</Form>
        <Form Tag="FAS">арабе´сачную</Form>
        <Form Tag="FIS">арабе´сачнай</Form>
        <Form Tag="FIS">арабе´сачнаю</Form>
        <Form Tag="FLS">арабе´сачнай</Form>
        <Form Tag="PNP">арабе´сачныя</Form>
        <Form Tag="PGP">арабе´сачных</Form>
        <Form Tag="PDP">арабе´сачным</Form>
        <Form Tag="PAP">арабе´сачныя</Form>
        <Form Tag="PIP">арабе´сачнымі</Form>
        <Form Tag="PLP">арабе´сачных</Form>
    </Paradigm>
    <Paradigm pdgId="0" Lemma="арагене´зіс" Tag="NCIINM1">
        <Form Tag="NS">арагене´зіс</Form>
        <Form Tag="GS">арагене´зісу</Form>
        <Form Tag="DS">арагене´зісу</Form>
        <Form Tag="AS">арагене´зіс</Form>
        <Form Tag="IS">арагене´зісам</Form>
        <Form Tag="LS">арагене´зісе</Form>
    </Paradigm>
    <Paradigm pdgId="0" Lemma="арама´т" Tag="NCIINM1">
        <Form Tag="NS">арама´т</Form>
        <Form Tag="GS">арама´ту</Form>
        <Form Tag="DS">арама´ту</Form>
        <Form Tag="AS">арама´т</Form>
        <Form Tag="IS">арама´там</Form>
        <Form Tag="LS">арама´це</Form>
        <Form Tag="NP">арама´ты</Form>
        <Form Tag="GP">арама´таў</Form>
        <Form Tag="DP">арама´там</Form>
        <Form Tag="AP">арама´ты</Form>
        <Form Tag="IP">арама´тамі</Form>
        <Form Tag="LP">арама´тах</Form>
    </Paradigm>
    <Paradigm pdgId="0" Lemma="аранда´тарыха" Tag="NCAPNF2">
        <Form Tag="NS">аранда´тарыха</Form>
        <Form Tag="GS">аранда´тарыхі</Form>
        <Form Tag="DS">аранда´тарысе</Form>
        <Form Tag="AS">аранда´тарыху</Form>
        <Form Tag="IS">аранда´тарыхай</Form>
        <Form Tag="IS">аранда´тарыхаю</Form>
        <Form Tag="LS">аранда´тарысе</Form>
        <Form Tag="NP">аранда´тарыхі</Form>
        <Form Tag="GP">аранда´тарых</Form>
        <Form Tag="DP">аранда´тарыхам</Form>
        <Form Tag="AP">аранда´тарых</Form>
        <Form Tag="IP">аранда´тарыхамі</Form>
        <Form Tag="LP">аранда´тарыхах</Form>
    </Paradigm>
    <Paradigm pdgId="0" Lemma="арандо´ваны" Tag="PPPP">
        <Form Tag="MNS">арандо´ваны</Form>
        <Form Tag="MGS">арандо´ванага</Form>
        <Form Tag="MDS">арандо´ванаму</Form>
        <Form Tag="MAS">арандо´ваны</Form>
        <Form Tag="MAS">арандо´ванага</Form>
        <Form Tag="MIS">арандо´ваным</Form>
        <Form Tag="MLS">арандо´ваным</Form>
        <Form Tag="NNS">арандо´ванае</Form>
        <Form Tag="NGS">арандо´ванага</Form>
        <Form Tag="NDS">арандо´ванаму</Form>
        <Form Tag="NAS">арандо´ванае</Form>
        <Form Tag="NIS">арандо´ваным</Form>
        <Form Tag="NLS">арандо´ваным</Form>
        <Form Tag="FNS">арандо´ваная</Form>
        <Form Tag="FGS">арандо´ванай</Form>
        <Form Tag="FGS">арандо´ванае</Form>
        <Form Tag="FDS">арандо´ванай</Form>
        <Form Tag="FAS">арандо´ваную</Form>
        <Form Tag="FIS">арандо´ванай</Form>
        <Form Tag="FIS">арандо´ванаю</Form>
        <Form Tag="FLS">арандо´ванай</Form>
        <Form Tag="PNP">арандо´ваныя</Form>
        <Form Tag="PGP">арандо´ваных</Form>
        <Form Tag="PDP">арандо´ваным</Form>
        <Form Tag="PAP">арандо´ваныя</Form>
        <Form Tag="PAP">арандо´ваных</Form>
        <Form Tag="PIP">арандо´ванымі</Form>
        <Form Tag="PLP">арандо´ваных</Form>
    </Paradigm>
    <Paradigm pdgId="0" Lemma="арандо´ваны" Tag="AXP">
        <Form Tag="MNS">арандо´ваны</Form>
        <Form Tag="MGS">арандо´ванага</Form>
        <Form Tag="MDS">арандо´ванаму</Form>
        <Form Tag="MAS">арандо´ваны</Form>
        <Form Tag="MIS">арандо´ваным</Form>
        <Form Tag="MLS">арандо´ваным</Form>
        <Form Tag="NNS">арандо´ванае</Form>
        <Form Tag="NGS">арандо´ванага</Form>
        <Form Tag="NDS">арандо´ванаму</Form>
        <Form Tag="NAS">арандо´ванае</Form>
        <Form Tag="NIS">арандо´ваным</Form>
        <Form Tag="NLS">арандо´ваным</Form>
        <Form Tag="FNS">арандо´ваная</Form>
        <Form Tag="FGS">арандо´ванай</Form>
        <Form Tag="FDS">арандо´ванай</Form>
        <Form Tag="FAS">арандо´ваную</Form>
        <Form Tag="FIS">арандо´ванай</Form>
        <Form Tag="FIS">арандо´ванаю</Form>
        <Form Tag="FLS">арандо´ванай</Form>
        <Form Tag="PNP">арандо´ваныя</Form>
        <Form Tag="PGP">арандо´ваных</Form>
        <Form Tag="PDP">арандо´ваным</Form>
        <Form Tag="PAP">арандо´ваныя</Form>
        <Form Tag="PIP">арандо´ванымі</Form>
        <Form Tag="PLP">арандо´ваных</Form>
    </Paradigm>
    <Paradigm pdgId="0" Lemma="арахнало´гія" Tag="NCIINF2">
        <Form Tag="NS">арахнало´гія</Form>
        <Form Tag="GS">арахнало´гіі</Form>
        <Form Tag="DS">арахнало´гіі</Form>
        <Form Tag="AS">арахнало´гію</Form>
        <Form Tag="IS">арахнало´гіяй</Form>
        <Form Tag="IS">арахнало´гіяю</Form>
        <Form Tag="LS">арахнало´гіі</Form>
    </Paradigm>
    <Paradigm pdgId="0" Lemma="арганізава´нне" Tag="NCIINN1">
        <Form Tag="NS">арганізава´нне</Form>
        <Form Tag="GS">арганізава´ння</Form>
        <Form Tag="DS">арганізава´нню</Form>
        <Form Tag="AS">арганізава´нне</Form>
        <Form Tag="IS">арганізава´ннем</Form>
        <Form Tag="LS">арганізава´нні</Form>
    </Paradigm>
    <Paradigm pdgId="0" Lemma="арганізацы´йна-педагагі´чны" Tag="ARP">
        <Form Tag="MNS">арганізацы´йна-педагагі´чны</Form>
        <Form Tag="MGS">арганізацы´йна-педагагі´чнага</Form>
        <Form Tag="MDS">арганізацы´йна-педагагі´чнаму</Form>
        <Form Tag="MAS">арганізацы´йна-педагагі´чны</Form>
        <Form Tag="MAS">арганізацы´йна-педагагі´чнага</Form>
        <Form Tag="MIS">арганізацы´йна-педагагі´чным</Form>
        <Form Tag="MLS">арганізацы´йна-педагагі´чным</Form>
        <Form Tag="NNS">арганізацы´йна-педагагі´чнае</Form>
        <Form Tag="NGS">арганізацы´йна-педагагі´чнага</Form>
        <Form Tag="NDS">арганізацы´йна-педагагі´чнаму</Form>
        <Form Tag="NAS">арганізацы´йна-педагагі´чнае</Form>
        <Form Tag="NIS">арганізацы´йна-педагагі´чным</Form>
        <Form Tag="NLS">арганізацы´йна-педагагі´чным</Form>
        <Form Tag="FNS">арганізацы´йна-педагагі´чная</Form>
        <Form Tag="FGS">арганізацы´йна-педагагі´чнай</Form>
        <Form Tag="FGS">арганізацы´йна-педагагі´чнае</Form>
        <Form Tag="FDS">арганізацы´йна-педагагі´чнай</Form>
        <Form Tag="FAS">арганізацы´йна-педагагі´чную</Form>
        <Form Tag="FIS">арганізацы´йна-педагагі´чнай</Form>
        <Form Tag="FIS">арганізацы´йна-педагагі´чнаю</Form>
        <Form Tag="FLS">арганізацы´йна-педагагі´чнай</Form>
        <Form Tag="PNP">арганізацы´йна-педагагі´чныя</Form>
        <Form Tag="PGP">арганізацы´йна-педагагі´чных</Form>
        <Form Tag="PDP">арганізацы´йна-педагагі´чным</Form>
        <Form Tag="PAP">арганізацы´йна-педагагі´чныя</Form>
        <Form Tag="PIP">арганізацы´йна-педагагі´чнымі</Form>
        <Form Tag="PLP">арганізацы´йна-педагагі´чных</Form>
    </Paradigm>
    <Paradigm pdgId="0" Lemma="аркушо´вы" Tag="ARP">
        <Form Tag="MNS">аркушо´вы</Form>
        <Form Tag="MGS">аркушо´вага</Form>
        <Form Tag="MDS">аркушо´ваму</Form>
        <Form Tag="MAS">аркушо´вы</Form>
        <Form Tag="MIS">аркушо´вым</Form>
        <Form Tag="MLS">аркушо´вым</Form>
        <Form Tag="NNS">аркушо´вае</Form>
        <Form Tag="NGS">аркушо´вага</Form>
        <Form Tag="NDS">аркушо´ваму</Form>
        <Form Tag="NAS">аркушо´вае</Form>
        <Form Tag="NIS">аркушо´вым</Form>
        <Form Tag="NLS">аркушо´вым</Form>
        <Form Tag="FNS">аркушо´вая</Form>
        <Form Tag="FGS">аркушо´вай</Form>
        <Form Tag="FGS">аркушо´вае</Form>
        <Form Tag="FDS">аркушо´вай</Form>
        <Form Tag="FAS">аркушо´вую</Form>
        <Form Tag="FIS">аркушо´вай</Form>
        <Form Tag="FIS">аркушо´ваю</Form>
        <Form Tag="FLS">аркушо´вай</Form>
        <Form Tag="PNP">аркушо´выя</Form>
        <Form Tag="PGP">аркушо´вых</Form>
        <Form Tag="PDP">аркушо´вым</Form>
        <Form Tag="PAP">аркушо´выя</Form>
        <Form Tag="PIP">аркушо´вымі</Form>
        <Form Tag="PLP">аркушо´вых</Form>
    </Paradigm>
    <Paradigm pdgId="0" Lemma="армрэ´стлінг" Tag="NCIINM1">
        <Form Tag="NS">армрэ´стлінг</Form>
        <Form Tag="GS">армрэ´стлінгу</Form>
        <Form Tag="DS">армрэ´стлінгу</Form>
        <Form Tag="AS">армрэ´стлінг</Form>
        <Form Tag="IS">армрэ´стлінгам</Form>
        <Form Tag="LS">армрэ´стлінгу</Form>
    </Paradigm>
    <Paradigm pdgId="0" Lemma="артры´тык" Tag="NCAPNM1">
        <Form Tag="NS">артры´тык</Form>
        <Form Tag="GS">артры´тыка</Form>
        <Form Tag="DS">артры´тыку</Form>
        <Form Tag="AS">артры´тыка</Form>
        <Form Tag="IS">артры´тыкам</Form>
        <Form Tag="LS">артры´тыку</Form>
        <Form Tag="NP">артры´тыкі</Form>
        <Form Tag="GP">артры´тыкаў</Form>
        <Form Tag="DP">артры´тыкам</Form>
        <Form Tag="AP">артры´тыкаў</Form>
        <Form Tag="IP">артры´тыкамі</Form>
        <Form Tag="LP">артры´тыках</Form>
    </Paradigm>
    <Paradigm pdgId="0" Lemma="ару´д" Tag="NCIINM1">
        <Form Tag="NS">ару´д</Form>
        <Form Tag="GS">ару´да</Form>
        <Form Tag="DS">ару´ду</Form>
        <Form Tag="AS">ару´д</Form>
        <Form Tag="IS">ару´дам</Form>
        <Form Tag="LS">ару´дзе</Form>
        <Form Tag="NP">ару´ды</Form>
        <Form Tag="GP">ару´даў</Form>
        <Form Tag="DP">ару´дам</Form>
        <Form Tag="AP">ару´ды</Form>
        <Form Tag="IP">ару´дамі</Form>
        <Form Tag="LP">ару´дах</Form>
    </Paradigm>
    <Paradigm pdgId="0" Lemma="архаі´стыка" Tag="NCIINF2">
        <Form Tag="NS">архаі´стыка</Form>
        <Form Tag="GS">архаі´стыкі</Form>
        <Form Tag="DS">архаі´стыцы</Form>
        <Form Tag="AS">архаі´стыку</Form>
        <Form Tag="IS">архаі´стыкай</Form>
        <Form Tag="IS">архаі´стыкаю</Form>
        <Form Tag="LS">архаі´стыцы</Form>
    </Paradigm>
    <Paradigm pdgId="0" Lemma="архімільяне´р" Tag="NCAPNM1">
        <Form Tag="NS">архімільяне´р</Form>
        <Form Tag="GS">архімільяне´ра</Form>
        <Form Tag="DS">архімільяне´ру</Form>
        <Form Tag="AS">архімільяне´ра</Form>
        <Form Tag="IS">архімільяне´рам</Form>
        <Form Tag="LS">архімільяне´ру</Form>
        <Form Tag="NP">архімільяне´ры</Form>
        <Form Tag="GP">архімільяне´раў</Form>
        <Form Tag="DP">архімільяне´рам</Form>
        <Form Tag="AP">архімільяне´раў</Form>
        <Form Tag="IP">архімільяне´рамі</Form>
        <Form Tag="LP">архімільяне´рах</Form>
    </Paradigm>
    <Paradigm pdgId="0" Lemma="арцыбі´скуп" Tag="NCAPNM1">
        <Form Tag="NS">арцыбі´скуп</Form>
        <Form Tag="GS">арцыбі´скупа</Form>
        <Form Tag="DS">арцыбі´скупу</Form>
        <Form Tag="AS">арцыбі´скупа</Form>
        <Form Tag="IS">арцыбі´скупам</Form>
        <Form Tag="LS">арцыбі´скупу</Form>
        <Form Tag="LS">арцыбі´скупе</Form>
        <Form Tag="NP">арцыбі´скупы</Form>
        <Form Tag="GP">арцыбі´скупаў</Form>
        <Form Tag="DP">арцыбі´скупам</Form>
        <Form Tag="AP">арцыбі´скупаў</Form>
        <Form Tag="IP">арцыбі´скупамі</Form>
        <Form Tag="LP">арцыбі´скупах</Form>
    </Paradigm>
    <Paradigm pdgId="0" Lemma="арышто´ваны" Tag="ARP">
        <Form Tag="MNS">арышто´ваны</Form>
        <Form Tag="MGS">арышто´ванага</Form>
        <Form Tag="MDS">арышто´ванаму</Form>
        <Form Tag="MAS">арышто´ваны</Form>
        <Form Tag="MAS">арышто´ванага</Form>
        <Form Tag="MIS">арышто´ваным</Form>
        <Form Tag="MLS">арышто´ваным</Form>
        <Form Tag="NNS">арышто´ванае</Form>
        <Form Tag="NGS">арышто´ванага</Form>
        <Form Tag="NDS">арышто´ванаму</Form>
        <Form Tag="NAS">арышто´ванае</Form>
        <Form Tag="NIS">арышто´ваным</Form>
        <Form Tag="NLS">арышто´ваным</Form>
        <Form Tag="FNS">арышто´ваная</Form>
        <Form Tag="FGS">арышто´ванай</Form>
        <Form Tag="FGS">арышто´ванае</Form>
        <Form Tag="FDS">арышто´ванай</Form>
        <Form Tag="FAS">арышто´ваную</Form>
        <Form Tag="FIS">арышто´ванай</Form>
        <Form Tag="FIS">арышто´ванаю</Form>
        <Form Tag="FLS">арышто´ванай</Form>
        <Form Tag="PNP">арышто´ваныя</Form>
        <Form Tag="PGP">арышто´ваных</Form>
        <Form Tag="PDP">арышто´ваным</Form>
        <Form Tag="PAP">арышто´ваныя</Form>
        <Form Tag="PIP">арышто´ванымі</Form>
        <Form Tag="PLP">арышто´ваных</Form>
    </Paradigm>
    <Paradigm pdgId="0" Lemma="арышто´ваны" Tag="PPPP">
        <Form Tag="MNS">арышто´ваны</Form>
        <Form Tag="MGS">арышто´ванага</Form>
        <Form Tag="MDS">арышто´ванаму</Form>
        <Form Tag="MAS">арышто´ваны</Form>
        <Form Tag="MAS">арышто´ванага</Form>
        <Form Tag="MIS">арышто´ваным</Form>
        <Form Tag="MLS">арышто´ваным</Form>
        <Form Tag="NNS">арышто´ванае</Form>
        <Form Tag="NGS">арышто´ванага</Form>
        <Form Tag="NDS">арышто´ванаму</Form>
        <Form Tag="NAS">арышто´ванае</Form>
        <Form Tag="NIS">арышто´ваным</Form>
        <Form Tag="NLS">арышто´ваным</Form>
        <Form Tag="FNS">арышто´ваная</Form>
        <Form Tag="FGS">арышто´ванай</Form>
        <Form Tag="FGS">арышто´ванае</Form>
        <Form Tag="FDS">арышто´ванай</Form>
        <Form Tag="FAS">арышто´ваную</Form>
        <Form Tag="FIS">арышто´ванай</Form>
        <Form Tag="FIS">арышто´ванаю</Form>
        <Form Tag="FLS">арышто´ванай</Form>
        <Form Tag="PNP">арышто´ваныя</Form>
        <Form Tag="PGP">арышто´ваных</Form>
        <Form Tag="PDP">арышто´ваным</Form>
        <Form Tag="PAP">арышто´ваныя</Form>
        <Form Tag="PAP">арышто´ваных</Form>
        <Form Tag="PIP">арышто´ванымі</Form>
        <Form Tag="PLP">арышто´ваных</Form>
    </Paradigm>
    <Paradigm pdgId="0" Lemma="арышто´ваны" Tag="NCAPNS5">
        <Form Tag="MNS">арышто´ваны</Form>
        <Form Tag="MGS">арышто´ванага</Form>
        <Form Tag="MDS">арышто´ванаму</Form>
        <Form Tag="MAS">арышто´ванага</Form>
        <Form Tag="MIS">арышто´ваным</Form>
        <Form Tag="MLS">арышто´ваным</Form>
        <Form Tag="PNP">арышто´ваныя</Form>
        <Form Tag="PGP">арышто´ваных</Form>
        <Form Tag="PDP">арышто´ваным</Form>
        <Form Tag="PAP">арышто´ваных</Form>
        <Form Tag="PIP">арышто´ванымі</Form>
        <Form Tag="PLP">арышто´ваных</Form>
    </Paradigm>
    <Paradigm pdgId="0" Lemma="арэ´скі" Tag="ARP">
        <Form Tag="MNS">арэ´скі</Form>
        <Form Tag="MGS">арэ´скага</Form>
        <Form Tag="MDS">арэ´скаму</Form>
        <Form Tag="MAS">арэ´скі</Form>
        <Form Tag="MAS">арэ´скага</Form>
        <Form Tag="MIS">арэ´скім</Form>
        <Form Tag="MLS">арэ´скім</Form>
        <Form Tag="NNS">арэ´скае</Form>
        <Form Tag="NGS">арэ´скага</Form>
        <Form Tag="NDS">арэ´скаму</Form>
        <Form Tag="NAS">арэ´скае</Form>
        <Form Tag="NIS">арэ´скім</Form>
        <Form Tag="NLS">арэ´скім</Form>
        <Form Tag="FNS">арэ´ская</Form>
        <Form Tag="FGS">арэ´скай</Form>
        <Form Tag="FGS">арэ´скае</Form>
        <Form Tag="FDS">арэ´скай</Form>
        <Form Tag="FAS">арэ´скую</Form>
        <Form Tag="FIS">арэ´скай</Form>
        <Form Tag="FIS">арэ´скаю</Form>
        <Form Tag="FLS">арэ´скай</Form>
        <Form Tag="PNP">арэ´скія</Form>
        <Form Tag="PGP">арэ´скіх</Form>
        <Form Tag="PDP">арэ´скім</Form>
        <Form Tag="PAP">арэ´скія</Form>
        <Form Tag="PIP">арэ´скімі</Form>
        <Form Tag="PLP">арэ´скіх</Form>
    </Paradigm>
</Wordlist>
