<?xml version="1.0" encoding="UTF-8" standalone="yes"?>
<Wordlist>
    <Paradigm pdgId="1214305" lemma="аббі+ць" tag="VTPNX">
        <Variant id="a" pravapis="A2008" lemma="аббі+ць">
            <Slounik name="piskunou2012" idx="431">{b}аббі´ць{/b} {i}зак.{/i}, абаб’ю´, -б’е´, -б’яце´ /// v2{sup}12{/sup} B/</Slounik>
            <Form tag="0">аббі+ць</Form>
            <Form tag="F1S">абаб'ю+</Form>
            <Form tag="F2S">абаб'е+ш</Form>
            <Form tag="F3S">абаб'е+</Form>
            <Form tag="F1P">абаб'ё+м</Form>
            <Form tag="F2P">абаб'яце+</Form>
            <Form tag="F3P">абаб'ю+ць</Form>
            <Form tag="PMS">аббі+ў</Form>
            <Form tag="PFS">аббі+ла</Form>
            <Form tag="PNS">аббі+ла</Form>
            <Form tag="PXP">аббі+лі</Form>
            <Form tag="I2S">аббі+</Form>
            <Form tag="I2P">аббі+це</Form>
            <Form tag="PG">аббі+ўшы</Form>
        </Variant>
    </Paradigm>
</Wordlist>
